[
    {
        "name": "Group Workout Instructor",
        "company": "Places for People",
        "location": "Newport Pagnell MK16+8 locations",
        "url": "https://uk.indeed.com/rc/clk?jk=dcad7aaa3209dd84&fccid=2fd14a756422e2c0&vjs=3",
        "summary": "\nYou will be comfortable working with customers of all abilities, no matter what stage they are in their fitness journey.\n",
        "creation_date": "PostedPosted 1 day ago",
        "saved_date": "2023-06-17"
    },
    {
        "name": "Fitness Consultant",
        "company": "University of Surrey",
        "location": "Hybrid remote in Guildford",
        "url": "https://uk.indeed.com/rc/clk?jk=a2b13b6a13caa5d7&fccid=3250454c2fffab4f&vjs=3",
        "summary": "\nThe post-holder will ensure the delivery of high-quality fitness activities and guest service, as well as the ongoing development of the fitness operation.\n",
        "creation_date": "PostedPosted 3 days ago",
        "saved_date": "2023-06-17"
    },
    {
        "name": "Climbing Instructor",
        "company": "Places for People",
        "location": "The Bridge+1 location",
        "url": "https://uk.indeed.com/rc/clk?jk=526364918951b23b&fccid=2fd14a756422e2c0&vjs=3",
        "summary": "\nYou will deliver a thorough safety briefing before all sessions to ensure that the participants are fully aware of all safety measures before taking part and\u2026\n",
        "creation_date": "PostedPosted 3 days ago",
        "saved_date": "2023-06-17"
    },
    {
        "name": "Band 5 Exercise Physiologist/Instructor - Cardiac Rehabilitation",
        "company": "University Hospitals Birmingham",
        "location": "Birmingham B15",
        "url": "https://uk.indeed.com/rc/clk?jk=8745d3e198843626&fccid=a34d2125adf30bc6&vjs=3",
        "summary": "\nIt is essential that the successful candidate has a BSc /BA (Hons) in Sports and Exercise Science/Therapy or related field and hold a recognised REPS level 3\u2026\n",
        "creation_date": "PostedPosted 9 days ago",
        "saved_date": "2023-06-17"
    },
    {
        "name": "LSD156 - Gym Instructor",
        "company": "YMCA Black Country Group",
        "location": "West Bromwich",
        "url": "https://uk.indeed.com/rc/clk?jk=11726ce3f996d818&fccid=cff6c2b12d7dc183&vjs=3",
        "summary": "\nLevel 2 gym instructor qualification.\nDelivering gym inductions/ fitness activity.\nTo assist in the smooth day-to-day running of the gym and fitness facilities.\n",
        "creation_date": "PostedPosted 3 days ago",
        "saved_date": "2023-06-17"
    },
    {
        "name": "Lecturer in Sport",
        "company": "Truro and Penwith College",
        "location": "Truro",
        "url": "https://uk.indeed.com/rc/clk?jk=5f306ea0779802d0&fccid=bf52db5e6a56ef13&vjs=3",
        "summary": "\nThe successful candidate will be required to teach across a range of academic and vocational courses including Level 3 BTEC Extended Diplomas in Sport and\u2026\n",
        "creation_date": "PostedPosted 7 days ago",
        "saved_date": "2023-06-17"
    },
    {
        "name": "Instructor (Spin)",
        "company": "YMCA",
        "location": "Lytham St. Annes FY8",
        "url": "https://uk.indeed.com/rc/clk?jk=4f48176c7465344d&fccid=cff6c2b12d7dc183&vjs=3",
        "summary": "\nSupport members in achieving their fitness goals.\nYour day will consist of\u2026.\nDeliver a high standard, quality service in discipline.\n",
        "creation_date": "PostedPosted 30+ days ago",
        "saved_date": "2023-06-17"
    },
    {
        "name": "Gym Instructor",
        "company": "Jubilee Hall Trust",
        "location": "London",
        "url": "https://uk.indeed.com/rc/clk?jk=b4efebec64cadd6a&fccid=bdfd65819b6f66d2&vjs=3",
        "summary": "\nAs well as being the first point of contact for all individuals coming into the gym.\nSupporting Duty Managers in the operation of the gym.\n",
        "creation_date": "PostedPosted 10 days ago",
        "saved_date": "2023-06-17"
    },
    {
        "name": "Gym Instructor",
        "company": "Horizon Leisure Centres",
        "location": "Waterlooville",
        "url": "https://uk.indeed.com/rc/clk?jk=36f85fc6fd382f74&fccid=bd92564eb6567d89&vjs=3",
        "summary": "\nTo ensure the gym and fitness equipment is kept clean and tidy as per the cleaning schedule.\nTo maintain fitness equipment and update the maintenance log.\n",
        "creation_date": "PostedPosted 30+ days ago",
        "saved_date": "2023-06-17"
    },
    {
        "name": "Sports Hub Trainee Manager/Gym Instructor",
        "company": "Kings College Guildford",
        "location": "Guildford",
        "url": "https://uk.indeed.com/company/Kings-College-Guildford/jobs/Hub-Manager-08d15286710a0ca6?fccid=9158372005c442fd&vjs=3",
        "summary": "\nNEW COMMUNITY SPORTS HUB AND GYM*.\nStaff will be required to work evenings and/or weekends.\nAll successful applicants will be required to undertake an Enhanced\u2026\n",
        "creation_date": "EmployerActive 12 days ago",
        "saved_date": "2023-06-17"
    },
    {
        "name": "Group Exercise Instructor",
        "company": "Halo Leisure",
        "location": "Herefordshire",
        "url": "https://uk.indeed.com/rc/clk?jk=a2d0715fc0c2fd31&fccid=fc1ea498d09e3021&vjs=3",
        "summary": "\nEducate customers on various aspects of fitness relating to the classes delivered.\nReporting to the General and Customer Service Manager of the centre, you will\u2026\n",
        "creation_date": "PostedPosted 4 days ago",
        "saved_date": "2023-06-17"
    },
    {
        "name": "Paddlesports Instructor",
        "company": "PGL Travel",
        "location": "Hailsham+13 locations",
        "url": "https://uk.indeed.com/rc/clk?jk=ef5a7c583af28f90&fccid=24ac9d95c06227dd&vjs=3",
        "summary": "\nExcellent rates of pay of up to \u00a310.90 per hour for entry level roles.\nAn accommodation & meal package available (optional) at a generous rate.\n",
        "creation_date": "PostedPosted 30+ days ago",
        "saved_date": "2023-06-17"
    },
    {
        "name": "ACTIVITIES INSTRUCTOR",
        "company": "Carnegie Club",
        "location": "Dornoch IV25",
        "url": "https://uk.indeed.com/rc/clk?jk=5c13e7d132a01442&fccid=902dcfa1c425a295&vjs=3",
        "summary": "\nComplimentary use of staff gym and fitness classes.\nReporting to the Sporting Activities Manager, you\u2019ll be responsible for the day-to-day instruction and\u2026\n",
        "creation_date": "PostedPosted 23 days ago",
        "saved_date": "2023-06-17"
    },
    {
        "name": "Fitness Consultant",
        "company": "Wiltshire Council",
        "location": "Devizes+1 location",
        "url": "https://uk.indeed.com/rc/clk?jk=b2ae9cb10da5d7b2&fccid=8274b9835447fd24&vjs=3",
        "summary": "\nAlong with experience within the fitness industry, you should also have a minimum of a Level 2 Fitness Instructor qualification and be REPs registered.\n",
        "creation_date": "PostedPosted 30+ days ago",
        "saved_date": "2023-06-17"
    },
    {
        "name": "Weekly Aqua Instructor",
        "company": "The Goodwood Estate",
        "location": "Chichester",
        "url": "https://uk.indeed.com/rc/clk?jk=bc5293c3c0e40662&fccid=51ec3a9b3ddc271f&vjs=3",
        "summary": "\nYou will be enthusiastic, professional and have good industry knowledge, with the ability to instruct water based classes.\n6 months minimum of experience.\n",
        "creation_date": "PostedPosted 30+ days ago",
        "saved_date": "2023-06-17"
    },
    {
        "name": "Pilates Instructor & PT Job Vacancy",
        "company": "Ten Health & Fitness",
        "location": "London",
        "url": "https://uk.indeed.com/rc/clk?jk=f6a4e87f02c66838&fccid=7c5d6893053f9fe3&vjs=3",
        "summary": "\nMinimum level 3 in Fitness, PT, or equivalent qualification.\nAssisting the marketing department where necessary, including; attending events, proactive use of\u2026\n",
        "creation_date": "PostedPosted 30+ days ago",
        "saved_date": "2023-06-17"
    },
    {
        "name": "Casual Fitness Consultant - Register",
        "company": "West-Norfolk",
        "location": "Norfolk",
        "url": "https://uk.indeed.com/rc/clk?jk=5dcb95213c8fbdd5&fccid=e6e675050eaffcd1&vjs=3",
        "summary": "\nYou will have level 2 gym instructor and qualification with experience and up to date knowledge.\nYou must also be able to effectively prescribe personal fitness\u2026\n",
        "creation_date": "PostedPosted 30+ days ago",
        "saved_date": "2023-06-17"
    },
    {
        "name": "Sports Instructors",
        "company": "Global Camps",
        "location": "London",
        "url": "https://uk.indeed.com/rc/clk?jk=03f71895eb918d46&fccid=35ce3b682ddc5c27&vjs=3",
        "summary": "\nThey are qualified and experienced sports instructors.\nThey are passionate about sport, health and fitness.\nPlan fun, structured sessions in a variety of sports\u2026\n",
        "creation_date": "PostedPosted 30+ days ago",
        "saved_date": "2023-06-17"
    },
    {
        "name": "Activity Instructor / Group Leader",
        "company": "PGL Travel",
        "location": "Northallerton+13 locations",
        "url": "https://uk.indeed.com/rc/clk?jk=512b2359009130be&fccid=24ac9d95c06227dd&vjs=3",
        "summary": "\nExcellent rates of pay of up to \u00a310.90 per hour for entry level roles.\nAn accommodation & meal package available (optional) at a generous rate.\n",
        "creation_date": "PostedPosted 30+ days ago",
        "saved_date": "2023-06-17"
    },
    {
        "name": "Junior Activities Instructor",
        "company": "Places for People",
        "location": "Haywards Heath RH16",
        "url": "https://uk.indeed.com/rc/clk?jk=31e41048f9fc1874&fccid=2fd14a756422e2c0&vjs=3",
        "summary": "\nFull Health & Fitness membership for you, a nominated adult and up to 4 juniors.\nFlexible working (including part time working, shift work and more).\n",
        "creation_date": "PostedPosted 30+ days ago",
        "saved_date": "2023-06-17"
    },
    {
        "name": "Leisure Attendant / Instructor",
        "company": "Aura Leisure and Libraries",
        "location": "Queensferry",
        "url": "https://uk.indeed.com/rc/clk?jk=7568d273aba17486&fccid=8227a1ba3e076b1a&vjs=3",
        "summary": "\nNVQ Level 1 or 2 teaching or coaching qualification in a relevant sport.\nEducation NVQ Level 2 Qualification in Sport and Recreation.\n",
        "creation_date": "PostedPosted 30+ days ago",
        "saved_date": "2023-06-17"
    },
    {
        "name": "Wellbeing Personal Trainer",
        "company": "Nuffield Health",
        "location": "Chesterfield",
        "url": "https://uk.indeed.com/rc/clk?jk=8fdd0702e5b362be&fccid=3aca82fe33580650&vjs=3",
        "summary": "\nConnect with and motivate members to reach their fitness goals and maintain a healthier lifestyle.\nSalary is based on 40 hours a week, made up of 32 Hours gym\u2026\n",
        "creation_date": "PostedPosted 2 days ago",
        "saved_date": "2023-06-17"
    },
    {
        "name": "Swim Instructor",
        "company": "Nuffield Health",
        "location": "Catterick Garrison+21 locations",
        "url": "https://uk.indeed.com/rc/clk?jk=e0f0465cc454c700&fccid=3aca82fe33580650&vjs=3",
        "summary": "\nAs a Swim Teacher at our Catterick , you\u2019ll need to have an ASA Level 2 or equivalent qualification, together with a good track record of coaching swimmers of\u2026\n",
        "creation_date": "PostedPosted 17 days ago",
        "saved_date": "2023-06-17"
    },
    {
        "name": "Health and Fitness Assistant",
        "company": "North Lincolnshire Council",
        "location": "Brigg DN20",
        "url": "https://uk.indeed.com/rc/clk?jk=a0227a17b833f1a6&fccid=3ab3337987121e06&vjs=3",
        "summary": "\nHealth & Fitness Assistants also deliver group sessions such as our junior gym programme and rig workout.\nHealth & Fitness Assistants work in NL Active gyms and\u2026\n",
        "creation_date": "PostedPosted 30+ days ago",
        "saved_date": "2023-06-17"
    },
    {
        "name": "Field Studies Instructor",
        "company": "PGL Travel",
        "location": "Weymouth",
        "url": "https://uk.indeed.com/rc/clk?jk=49bf8c158e90634d&fccid=24ac9d95c06227dd&vjs=3",
        "summary": "\nExcellent rates of pay of up to \u00a310.90 per hour for entry level roles.\nAn accommodation & meal package available (optional) at a generous rate.\n",
        "creation_date": "PostedPosted 30+ days ago",
        "saved_date": "2023-06-17"
    },
    {
        "name": "Yoga Instructor",
        "company": "Virgin Active",
        "location": "Brentwood CM13+1 location",
        "url": "https://uk.indeed.com/rc/clk?jk=069953dcf54d7e7a&fccid=a0cdc1728ba184cd&vjs=3",
        "summary": "\nYou check in with the club team often and always keep up to date with class policies and instructor procedures.\n",
        "creation_date": "PostedPosted 10 days ago",
        "saved_date": "2023-06-17"
    },
    {
        "name": "Swimming Instructor",
        "company": "Loughborough University",
        "location": "Loughborough",
        "url": "https://uk.indeed.com/rc/clk?jk=9e09e62896f6de7c&fccid=5ab93f939daefc0d&vjs=3",
        "summary": "\nWe are looking for exceptional individuals capable of providing a safe, clean environment and who delivers an excellent customer service experience that exceeds\u2026\n",
        "creation_date": "PostedPosted 30+ days ago",
        "saved_date": "2023-06-17"
    },
    {
        "name": "Sunday Aqua Instructor",
        "company": "Places for People",
        "location": "High Wycombe HP11",
        "url": "https://uk.indeed.com/rc/clk?jk=1ef46c780d8ab6e3&fccid=2fd14a756422e2c0&vjs=3",
        "summary": "\nYou will be comfortable working with customers of all abilities, no matter what stage they are in their fitness journey.\n",
        "creation_date": "PostedPosted 30+ days ago",
        "saved_date": "2023-06-17"
    },
    {
        "name": "Aqua Instructor",
        "company": "Virgin Active",
        "location": "London SW6+1 location",
        "url": "https://uk.indeed.com/rc/clk?jk=4a7a05d8f6e8aac9&fccid=a0cdc1728ba184cd&vjs=3",
        "summary": "\nYou have at least an NVQ Level 2 in Fitness or Aqua and an Aqua instructor qualification.\nYou check in with the club team often and always keep up to date with\u2026\n",
        "creation_date": "PostedPosted 3 days ago",
        "saved_date": "2023-06-17"
    },
    {
        "name": "Group Workout Instructor ( Aqua Fit)",
        "company": "Places for People",
        "location": "Wellingborough NN8",
        "url": "https://uk.indeed.com/rc/clk?jk=1a94731b57229d14&fccid=2fd14a756422e2c0&vjs=3",
        "summary": "\nYou will be comfortable working with customers of all abilities, no matter what stage they are in their fitness journey.\n",
        "creation_date": "PostedPosted 29 days ago",
        "saved_date": "2023-06-17"
    },
    {
        "name": "Cycle Instructor",
        "company": "Virgin Active",
        "location": "Sheffield S8+4 locations",
        "url": "https://uk.indeed.com/rc/clk?jk=1e0362f4a2ea5195&fccid=a0cdc1728ba184cd&vjs=3",
        "summary": "\nYou have at least an NVQ Level 2 in Fitness and an accredited Cycle specific instructor qualification.\nYou achieve agreed targets, of class occupancy and\u2026\n",
        "creation_date": "PostedPosted 23 days ago",
        "saved_date": "2023-06-17"
    },
    {
        "name": "Barre Instructor",
        "company": "Virgin Active",
        "location": "London NW7+1 location",
        "url": "https://uk.indeed.com/rc/clk?jk=839f11d86d799454&fccid=a0cdc1728ba184cd&vjs=3",
        "summary": "\nYou have at least an NVQ Level 2 in Fitness and the GroupXTraining Barre instructor qualification https://www.groupxtraining.com/shop/barre-fitness\u2026\n",
        "creation_date": "PostedPosted 23 days ago",
        "saved_date": "2023-06-17"
    },
    {
        "name": "Fitness Professional",
        "company": "Richmond Villages",
        "location": "Letcombe Regis",
        "url": "https://uk.indeed.com/rc/clk?jk=00860ee584747b03&fccid=865292a0b79c46da&vjs=3",
        "summary": "\nDeveloping and promoting organised events such as fitness challenges and group activities.\nAssisting members in setting and achieving their fitness goals,\u2026\n",
        "creation_date": "PostedPosted 30+ days ago",
        "saved_date": "2023-06-17"
    },
    {
        "name": "Senior Boxing Coach/Physical Activity Instructor (Mansfield)",
        "company": "SwitchUp",
        "location": "Mansfield NG18",
        "url": "https://uk.indeed.com/rc/clk?jk=070ba28610f61faf&fccid=1abc052c228540bb&vjs=3",
        "summary": "\nMansfield Community Hub is home to Mansfield School of Boxing and sister organisation Switch Up.\nThe salary is \u00a320.400 - \u00a322,000 pa for a full time role\u2026\n",
        "creation_date": "PostedPosted 7 days ago",
        "saved_date": "2023-06-17"
    },
    {
        "name": "Casual Cycle Instructor",
        "company": "The Royal Borough of Kingston upon Thames",
        "location": "Hybrid remote in Carshalton",
        "url": "https://uk.indeed.com/rc/clk?jk=567bb0697d2607d5&fccid=9ca25db8183dafb0&vjs=3",
        "summary": "\nAlso, all cycle instructors must train on to the Level 2 Award in Teaching Cycle Training, as published on register.ofqual.gov.uk.\n",
        "creation_date": "PostedPosted 30+ days ago",
        "saved_date": "2023-06-17"
    },
    {
        "name": "Activity Instructor/Group Leader (Lifeguard)",
        "company": "PGL Travel",
        "location": "Hailsham+1 location",
        "url": "https://uk.indeed.com/rc/clk?jk=542e6c85e50557f0&fccid=24ac9d95c06227dd&vjs=3",
        "summary": "\nExcellent rates of pay of up to \u00a310.90 per hour for entry level roles.\nAn accommodation & meal package available (optional) at a generous rate.\n",
        "creation_date": "PostedPosted 30+ days ago",
        "saved_date": "2023-06-17"
    },
    {
        "name": "Casual Health and Fitness Assistant",
        "company": "North Lincolnshire Council",
        "location": "Scunthorpe DN15",
        "url": "https://uk.indeed.com/rc/clk?jk=0be3000b803c2cf6&fccid=3ab3337987121e06&vjs=3",
        "summary": "\nShowing customers how to use our fitness equipment and explaining the benefits.\nSalary: \u00a310.79 per hour plus 10.7% in lieu of annual leave.\n",
        "creation_date": "PostedPosted 30+ days ago",
        "saved_date": "2023-06-17"
    },
    {
        "name": "Casual Cycle Instructor",
        "company": "London Borough of Sutton",
        "location": "Hybrid remote in Sutton",
        "url": "https://uk.indeed.com/rc/clk?jk=6fb9494b2ab8624d&fccid=19c17b971f2e2123&vjs=3",
        "summary": "\nAlso, all cycle instructors must train on to the Level 2 Award in Teaching Cycle Training, as published on register.ofqual.gov.uk.\n",
        "creation_date": "PostedPosted 30+ days ago",
        "saved_date": "2023-06-17"
    },
    {
        "name": "Body Pump Instructor",
        "company": "Virgin Active",
        "location": "Brentwood CM13",
        "url": "https://uk.indeed.com/rc/clk?jk=ad872327f16c2b3f&fccid=a0cdc1728ba184cd&vjs=3",
        "summary": "\nYou have at least an NVQ Level 2 in Fitness and a Les Mills Body Pump instructor qualification.\nYou achieve agreed targets, of class occupancy and instructor\u2026\n",
        "creation_date": "PostedPosted 10 days ago",
        "saved_date": "2023-06-17"
    },
    {
        "name": "EFL Teacher",
        "company": "PGL Travel",
        "location": "Grantham",
        "url": "https://uk.indeed.com/rc/clk?jk=8a13d993ef5e1dbd&fccid=24ac9d95c06227dd&vjs=3",
        "summary": "\nAn accommodation & meal package available (optional) at a generous rate.\nSome travel between our centres to facilitate our English language sessions may be\u2026\n",
        "creation_date": "PostedPosted 30+ days ago",
        "saved_date": "2023-06-17"
    },
    {
        "name": "Personal Trainer",
        "company": "Nuffield Health",
        "location": "West Byfleet",
        "url": "https://uk.indeed.com/rc/clk?jk=4aaaa3426c2f83a7&fccid=3aca82fe33580650&vjs=3",
        "summary": "\nCarry out high-quality inductions, Personal best programmes, group and personal training sessions, and general gym duties.\n",
        "creation_date": "PostedPosted 1 day ago",
        "saved_date": "2023-06-17"
    },
    {
        "name": "Sports Instructor (Primary School Opportunity)",
        "company": "GSL Education",
        "location": "Chelmsford",
        "url": "https://uk.indeed.com/rc/clk?jk=06fcbf76effa6c0e&fccid=48d9a0d482fd63a5&vjs=3",
        "summary": "\nDesign and deliver engaging sports lessons and activities for primary school students, promoting skill development, teamwork, and sportsmanship.\n",
        "creation_date": "PostedPosted 2 days ago",
        "saved_date": "2023-06-17"
    },
    {
        "name": "Swimming Instructors",
        "company": "Broxbourne Council",
        "location": "Cheshunt",
        "url": "https://uk.indeed.com/rc/clk?jk=eec9bcec219862a2&fccid=e966768577ee71e2&vjs=3",
        "summary": "\nA Swim England Level 2 teacher\u2019s qualification is the minimum qualification required.\nYou will also get free membership to the Council\u2019s leisure centres,\u2026\n",
        "creation_date": "PostedPosted 30+ days ago",
        "saved_date": "2023-06-17"
    },
    {
        "name": "Aqua Aerobics Teacher (Mp) Casual",
        "company": "Blackpool Council",
        "location": "Blackpool",
        "url": "https://uk.indeed.com/rc/clk?jk=6d931ecabc17e709&fccid=b9ff1ed564aeb44f&vjs=3",
        "summary": "\nSalary - NJC GRADE D PLUS MARKET SUPP (20.00 PH).\nEssentially you must possess an appropriate Aqua Aerobics qualification as you will be responsible for the\u2026\n",
        "creation_date": "PostedPosted 17 days ago",
        "saved_date": "2023-06-17"
    },
    {
        "name": "Swimming Instructor",
        "company": "Nuffield Health",
        "location": "Barrow-In-Furness+4 locations",
        "url": "https://uk.indeed.com/rc/clk?jk=dae42e7df5ff9c10&fccid=3aca82fe33580650&vjs=3",
        "summary": "\nASA Level 2 or an equivalent qualification, together with a track record of coaching swimmers of all ages and abilities.\nA track record of achieving targets.\n",
        "creation_date": "PostedPosted 9 days ago",
        "saved_date": "2023-06-17"
    },
    {
        "name": "Group Exercise and Swim Manager",
        "company": "Nuffield Health",
        "location": "Swindon",
        "url": "https://uk.indeed.com/rc/clk?jk=b3698eb093d50e4e&fccid=3aca82fe33580650&vjs=3",
        "summary": "\nYou\u2019ll have experience of a corporate or commercial fitness environment.\nIf you\u2019re passionate about fitness and wellbeing, you could take the lead on delivering\u2026\n",
        "creation_date": "PostedPosted 10 days ago",
        "saved_date": "2023-06-17"
    },
    {
        "name": "Reformer Pilates Instructor",
        "company": "Virgin Active",
        "location": "London SW19",
        "url": "https://uk.indeed.com/rc/clk?jk=33c8407849500f91&fccid=a0cdc1728ba184cd&vjs=3",
        "summary": "\nYou have at least an NVQ Level 3 Pilates instructor qualification.\nYou check in with the club team often and always keep up to date with class policies and\u2026\n",
        "creation_date": "PostedPosted 30 days ago",
        "saved_date": "2023-06-17"
    },
    {
        "name": "Swim Instructor",
        "company": "Virgin Active",
        "location": "Sheffield S8+1 location",
        "url": "https://uk.indeed.com/rc/clk?jk=19b37c67c3821d7d&fccid=a0cdc1728ba184cd&vjs=3",
        "summary": "\nFlexibility is required to meet the needs of the business; typical lessons take place after school or in the mornings for pre school, as well as weekends, and\u2026\n",
        "creation_date": "PostedPosted 4 days ago",
        "saved_date": "2023-06-17"
    },
    {
        "name": "Sailing Instructor",
        "company": "PGL Travel",
        "location": "Ryde+1 location",
        "url": "https://uk.indeed.com/rc/clk?jk=8412793699d75a5a&fccid=24ac9d95c06227dd&vjs=3",
        "summary": "\nYou\u2019ll be responsible for delivering fun & educational sessions to children and families; maintaining high levels of safety; training and supervising water\u2026\n",
        "creation_date": "PostedPosted 30+ days ago",
        "saved_date": "2023-06-17"
    },
    {
        "name": "Personal Training Apprenticeship - Lincoln",
        "company": "Lifetime Training",
        "location": "Lincoln LN2+1 location",
        "url": "https://uk.indeed.com/rc/clk?jk=6eb195af9f93c574&fccid=1b8719bf0816afc7&vjs=3",
        "summary": "\nWe have 5 other PT's here at energie fitness and 3 of them did their apprenticeships here.\nA passion for health and fitness is essential.\n",
        "creation_date": "PostedPosted 2 days ago",
        "saved_date": "2023-06-17"
    },
    {
        "name": "Physiotherapist / Pilates Instructor Hybrid",
        "company": "Ten Health & Fitness",
        "location": "London",
        "url": "https://uk.indeed.com/rc/clk?jk=2653765086730fd8&fccid=7c5d6893053f9fe3&vjs=3",
        "summary": "\nMinimum 2 years\u2019 experience in treating MSK conditions.\nUndertake comprehensive assessments of a great client base for MSK + Sports injuries/conditions in need\u2026\n",
        "creation_date": "PostedPosted 30+ days ago",
        "saved_date": "2023-06-17"
    },
    {
        "name": "Pilates Instructor",
        "company": "Virgin Active",
        "location": "Brentwood CM13",
        "url": "https://uk.indeed.com/rc/clk?jk=eac7d34c351e836d&fccid=a0cdc1728ba184cd&vjs=3",
        "summary": "\nYou have at least an NVQ Level 3 Pilates instructor qualification.\nYou check in with the club team often and always keep up to date with class policies and\u2026\n",
        "creation_date": "PostedPosted 10 days ago",
        "saved_date": "2023-06-17"
    },
    {
        "name": "Swim Teacher",
        "company": "Bannatyne",
        "location": "Leeds",
        "url": "https://uk.indeed.com/rc/clk?jk=c6a3643cab7ee110&fccid=deca7ade2822000d&vjs=3",
        "summary": "\nWe offer high quality lessons with great teacher to pupil ratios that meet and exceed ASA standards within the Learn to Swim framework.\n",
        "creation_date": "PostedPosted 7 days ago",
        "saved_date": "2023-06-17"
    },
    {
        "name": "Gymnastics & Trampoline Development Officer",
        "company": "Derbyshire County Council",
        "location": "Dronfield",
        "url": "https://uk.indeed.com/rc/clk?jk=d7936958dae5ecc6&fccid=e738246d157150d1&vjs=3",
        "summary": "\nBritish Gymnastics General Gymnastics Level 2 or Women\u2019s Artistic Level 2 or Gymnastics Activity Instructor.\nPre-School Gymnastics Level 2 or Pre-School add on\u2026\n",
        "creation_date": "PostedPosted 8 days ago",
        "saved_date": "2023-06-17"
    },
    {
        "name": "Swimming Teacher",
        "company": "Nuffield Health",
        "location": "Uxbridge",
        "url": "https://uk.indeed.com/rc/clk?jk=7b2e3f4f9613b339&fccid=3aca82fe33580650&vjs=3",
        "summary": "\nAs a Swim Teacher at our Stockley Park, you\u2019ll need to have an ASA Level 2 or equivalent qualification, together with a good track record of coaching swimmers\u2026\n",
        "creation_date": "PostedPosted 30+ days ago",
        "saved_date": "2023-06-17"
    },
    {
        "name": "Bootcamp Instructor | Online Training | Personal Training",
        "company": "RISE Fitness",
        "location": "Milton Keynes+19 locations",
        "url": "https://uk.indeed.com/company/RISE-Fitness/jobs/Training-Instructor-f472a698e8ae403d?fccid=4bccd46b250e244f&vjs=3",
        "summary": "\nRISE is a flexible mobile business designed to work in parks, open green spaces, and venues such as the local community hall.\nPart-time hours: 20 - 30 per week.\n",
        "creation_date": "EmployerActive 11 days ago",
        "saved_date": "2023-06-17"
    },
    {
        "name": "Spin Instructor",
        "company": "Anytime Fitness Chelsea",
        "location": "Chelsea SW10",
        "url": "https://uk.indeed.com/company/Anytime-Fitness/jobs/Instructor-bf10e1bf94190b69?fccid=fa9944eac2718763&vjs=3",
        "summary": "\nEngage with all participants.\nTo deliver an exciting Spin class to members.\n",
        "creation_date": "PostedPosted 2 days ago",
        "saved_date": "2023-06-17"
    },
    {
        "name": "Spin instructor",
        "company": "Dog House Fitness",
        "location": "London",
        "url": "https://uk.indeed.com/company/Dog-House-Fitness/jobs/Instructor-094b1db43d24c8e2?fccid=68fdbc404fc5852f&vjs=3",
        "summary": "\nHours are flexible to fit your schedule.\nPart-time hours: 4-6 per week.\nLondon: reliably commute or plan to relocate before starting work (required).\n",
        "creation_date": "EmployerActive 5 days ago",
        "saved_date": "2023-06-17"
    },
    {
        "name": "Lead Instructor",
        "company": "Third Space",
        "location": "London E14",
        "url": "https://uk.indeed.com/rc/clk?jk=f8ccfe0d2161eaf4&fccid=6ab11fb8bd4bab1b&vjs=3",
        "summary": "\nThey are highly motivated to not only deliver exceptional Group Exercise programmes, but are excited by spending the rest of their time showcasing the Third\u2026\n",
        "creation_date": "PostedPosted 1 day ago",
        "saved_date": "2023-06-17"
    },
    {
        "name": "Watersports Instructor in Cornwall",
        "company": "Cornwall Waverunner Safaris Ltd",
        "location": "Newquay",
        "url": "https://uk.indeed.com/company/Cornwall-Waverunner-Safaris-Ltd/jobs/Instructor-2d745eec59e40d57?fccid=4d783a4a0253888a&vjs=3",
        "summary": "\nAll applicants must be willing to work weekends and bank holidays.\nPrevious experience in the industry.\nConfidence in and on the water.\n",
        "creation_date": "EmployerActive 7 days ago",
        "saved_date": "2023-06-17"
    },
    {
        "name": "Gym Instructor",
        "company": "Armoury Gym",
        "location": "London NW3",
        "url": "https://uk.indeed.com/company/Jubilee-Hall-Trust/jobs/Instructor-08325896f0ce7d73?fccid=bdfd65819b6f66d2&vjs=3",
        "summary": "\nAs well as being the first point of contact for all individuals coming into the gym.\nSupporting Duty Managers in the operation of the gym.\n",
        "creation_date": "EmployerActive 3 days ago",
        "saved_date": "2023-06-17"
    },
    {
        "name": "Outdoor Activity Instructor",
        "company": "Serco Plc",
        "location": "Nottingham NG12",
        "url": "https://uk.indeed.com/company/Serco---Temps/jobs/Instructor-81fcef1901b6f340?fccid=72b4c0bd15805154&vjs=3",
        "summary": "\nWorking Hours:* Casual hours, mostly weekends and school holidays.\nYou will be the face and the first point of contact for our Outdoor Adventure Zone, making\u2026\n",
        "creation_date": "PostedPosted 30+ days ago",
        "saved_date": "2023-06-17"
    },
    {
        "name": "Gym and Class Instructor",
        "company": "HEALTHOUTFIT LTD",
        "location": "Aberdeen",
        "url": "https://uk.indeed.com/company/HEALTHOUTFIT-LTD/jobs/Instructor-6bceba3344033628?fccid=133be8a913d1a8d6&vjs=3",
        "summary": "\nFitness instructor: 2 years (required).\nREPs Level 2 qualification is essential together with current first aid certification and previous experience working\u2026\n",
        "creation_date": "PostedPosted 30+ days ago",
        "saved_date": "2023-06-17"
    },
    {
        "name": "Pool & Fitness Attendant",
        "company": "Trump Turnberry - Spa",
        "location": "Turnberry KA26",
        "url": "https://uk.indeed.com/rc/clk?jk=0ceba0181666e11e&fccid=ebb5a9e9afbe7d05&vjs=3",
        "summary": "\nWhere possible, provide personal training, gym instruction and fitness programmes for all guests and members, taking into account their needs and goals\u2026\n",
        "creation_date": "PostedPosted 25 days ago",
        "saved_date": "2023-06-17"
    },
    {
        "name": "Martial Arts Instructor",
        "company": "Full of Beans Children's Fitness & Sports Coaching",
        "location": "Newcastle upon Tyne",
        "url": "https://uk.indeed.com/company/Full-of-Beans-Fitness-Ltd/jobs/Martial-Arts-Instructor-c9009dd5cd859fa1?fccid=f61578951376e4a0&vjs=3",
        "summary": "\nYou will be delivering after school clubs, Curriculum PE & lunch time activities within our partner schools.\nIdeally you will drive to enable you to get to our\u2026\n",
        "creation_date": "EmployerActive 7 days ago",
        "saved_date": "2023-06-17"
    },
    {
        "name": "Martial Arts Instructor",
        "company": "Combined Defensive Arts Ltd",
        "location": "Cheltenham GL51",
        "url": "https://uk.indeed.com/company/Greenway-Property/jobs/Martial-Arts-Instructor-6967bc664bfe606f?fccid=7b981405ab0ba9d7&vjs=3",
        "summary": "\nAll instructors will require a DBS check and references will be taken.\nTeaching a mix of children\u2019s and adult\u2019s classes, our ideal candidate will be experienced\u2026\n",
        "creation_date": "PostedToday",
        "saved_date": "2023-06-17"
    },
    {
        "name": "Fitness Instructor",
        "company": "James Bickley Running",
        "location": "West Midlands+1 location",
        "url": "https://uk.indeed.com/company/James-Bickley-Running/jobs/Fitness-Instructor-1e3a458a750e716a?fccid=513038dbf3ef938a&vjs=3",
        "summary": "\nThe chosen canidate will be in charge of group fitness classes, predomintely adults ranging in age from young adults up to retired individuals.\n",
        "creation_date": "EmployerActive 8 days ago",
        "saved_date": "2023-06-17"
    },
    {
        "name": "Gym Instructor",
        "company": "Active Northumberland",
        "location": "Ashington NE63",
        "url": "https://uk.indeed.com/company/Active-Northumberland/jobs/Instructor-011d9d0d39cf5fbc?fccid=d4dfe2b4166df923&vjs=3",
        "summary": "\nConduct gym inductions, offer fitness advice and information to customers, and carry out fitness instruction in the gym in accordance with procedure.\n",
        "creation_date": "EmployerActive 3 days ago",
        "saved_date": "2023-06-17"
    },
    {
        "name": "Spin Instructor",
        "company": "ELITE Sports UK",
        "location": "Coventry",
        "url": "https://uk.indeed.com/company/ELITE-Sports-Development-Company/jobs/Instructor-6ff67bb922a846ee?fccid=17f4663a1761072c&vjs=3",
        "summary": "\nTo be successful as a spin instructor, you should be able to motivate all participants, regardless of their level of fitness.\nJob Types: Part-time, Freelance.\n",
        "creation_date": "EmployerActive 3 days ago",
        "saved_date": "2023-06-17"
    },
    {
        "name": "Group Exercise Instructor",
        "company": "Anytime Fitness Dalston",
        "location": "London E8",
        "url": "https://uk.indeed.com/company/Anytime-Fitness-Dalston/jobs/Fitness-Instructor-0f5ade32bd4e16ef?fccid=09c91b6a3400e5c5&vjs=3",
        "summary": "\nAnytime Fitness Dalston is looking for a CREATIVE AND ENTHUSIASTIC, NO NONSENSE class Instructor at our gym in the heart of Dalston to teach a morning class\u2026\n",
        "creation_date": "PostedPosted 30+ days ago",
        "saved_date": "2023-06-17"
    },
    {
        "name": "Martial Arts Instructor",
        "company": "AG Martial Arts",
        "location": "Bournemouth+1 location",
        "url": "https://uk.indeed.com/company/AG-Martial-Arts/jobs/Martial-Arts-Instructor-7593f316a85b1cdb?fccid=ec0586c9ac197e3e&vjs=3",
        "summary": "\nProviding high quality, engaging martial arts instruction to students of all ages and levels.\nPreparing lesson plans that align with our curriculum and guide\u2026\n",
        "creation_date": "EmployerActive 3 days ago",
        "saved_date": "2023-06-17"
    },
    {
        "name": "HEALTH & FITNESS MANAGER",
        "company": "OVERSTONE PARK LTD",
        "location": "Northampton",
        "url": "https://uk.indeed.com/company/OVERSTONE-PARK-LTD/jobs/Fitness-Manager-da63be6b7bcaa5d5?fccid=4549585d962869bb&vjs=3",
        "summary": "\nThe role requires high standards and the necessary operational qualifications such as Level 3-4 leisure related qualification.\n",
        "creation_date": "EmployerActive 3 days ago",
        "saved_date": "2023-06-17"
    },
    {
        "name": "Activity Instructor",
        "company": "South West Lakes Trust - NCS",
        "location": "Liskeard PL14",
        "url": "https://uk.indeed.com/company/South-West-Lakes-Trust---NCS/jobs/Instructor-e4ad9c9c4a685ca9?fccid=7f2c30622433895a&vjs=3",
        "summary": "\nA good level of physical fitness.\n1.3 DATES Working weeks will run from the 3rd July \u2013 1st September.\n1.4 HOURS Hours will be from 9am - 4pm Monday to\u2026\n",
        "creation_date": "EmployerActive 3 days ago",
        "saved_date": "2023-06-17"
    },
    {
        "name": "Kickboxing Instructor",
        "company": "TruBe",
        "location": "Twickenham+5 locations",
        "url": "https://uk.indeed.com/company/TruBe/jobs/Instructor-542363161aea2b67?fccid=fc5582771cde706e&vjs=3",
        "summary": "\nSuccessful candidates who gain entry on to the TruBe platform gain exposure to a wide range of fitness clients with various fitness goals.\n",
        "creation_date": "EmployerActive 3 days ago",
        "saved_date": "2023-06-17"
    },
    {
        "name": "Reformer Pilates Instructor",
        "company": "Club Pilates United Kingdom",
        "location": "London SE1",
        "url": "https://uk.indeed.com/company/Club-Pilates-United-Kingdom/jobs/Pilates-Instructor-681e65fc296f892b?fccid=f7a1ac5575bf7f05&vjs=3",
        "summary": "\nWe are looking for instructors with confidence in working with all level of clients to provide challenging, fitness-based Pilates classes in a safe manner.\n",
        "creation_date": "EmployerActive 3 days ago",
        "saved_date": "2023-06-17"
    },
    {
        "name": "Fitness Supervisor",
        "company": "Abbeycroft Leisure",
        "location": "Bury St. Edmunds",
        "url": "https://uk.indeed.com/company/Abbeycroft-Leisure/jobs/Fitness-Manager-555bbe0d63312bac?fccid=8a1458617e702823&vjs=3",
        "summary": "\nWk 3 Mon05:45-14:15 Tues 14:15-22:15 Weds 17:15-22:15 Sat07:45-16:15 Sun 07:45-16:15.\nWk 2 Mon05:45-13:15 Thurs 13:15-22:15 Fri 16:15-22:15 *Sat\u2026\n",
        "creation_date": "PostedToday",
        "saved_date": "2023-06-17"
    },
    {
        "name": "Zumba Instructor",
        "company": "Bromley Fitness Centre",
        "location": "Bromley BR1",
        "url": "https://uk.indeed.com/company/Bromley-Fitness-Centre/jobs/Fitness-Instructor-5e808a5f43c24b1f?fccid=fa76b97d8ccc2a11&vjs=3",
        "summary": "\nBromley Fitness Centre are looking for a new Zumba Instructor available to lead a 1 hour zumba class every Friday evening.\nPart-time hours: 1 per week.\n",
        "creation_date": "EmployerActive 1 day ago",
        "saved_date": "2023-06-17"
    },
    {
        "name": "Gym Instructor",
        "company": "All Warriors Gym",
        "location": "Ayr KA8",
        "url": "https://uk.indeed.com/company/All-Womans-Gym/jobs/Instructor-f940b2fa8bfd59fb?fccid=3dfe7bb1d3bf6d77&vjs=3",
        "summary": "\nSupporting them with fitness and weight loss.\nAnd being a friend to any member who may have struggled wIth mental health weight loss and fitness.\n",
        "creation_date": "EmployerActive 14 days ago",
        "saved_date": "2023-06-17"
    },
    {
        "name": "Gym Instructor",
        "company": "Peterborough Limited",
        "location": "Peterborough",
        "url": "https://uk.indeed.com/company/Peterborough-Limited/jobs/Instructor-ceaf4feec9147ee7?fccid=9db42030a6a544c0&vjs=3",
        "summary": "\nA current Level 2 Register of Exercise professional (REPS) or ability to gain (with support from the company) in 12 weeks (E).\nPart-time hours: 0-37 per week.\n",
        "creation_date": "EmployerActive 3 days ago",
        "saved_date": "2023-06-17"
    },
    {
        "name": "Kickboxing Instructor",
        "company": "Temple Martial Arts",
        "location": "West Midlands+1 location",
        "url": "https://uk.indeed.com/company/Temple-Martial-Arts/jobs/Instructor-43df4c717b2e1143?fccid=304861ffc1628e38&vjs=3",
        "summary": "\nAn ideal candidate will be comfortable delivering martial arts sessions to separate groups of children and adults with varying abilities.\n",
        "creation_date": "EmployerActive 1 day ago",
        "saved_date": "2023-06-17"
    },
    {
        "name": "Exercise Referral Instructor",
        "company": "GLL",
        "location": "Bath",
        "url": "https://uk.indeed.com/rc/clk?jk=f54a2481693e0d89&fccid=4b4c2ac64a4ed95e&vjs=3",
        "summary": "\nThat means you will need to be CIMPSA registered with an NVQ Level 3 Fitness Instructor, a Level 3 GP Referral qualification and experience of delivering\u2026\n",
        "creation_date": "PostedPosted 2 days ago",
        "saved_date": "2023-06-17"
    },
    {
        "name": "Sport & Fitness Assistant",
        "company": "Unique Fitness, University of Bradford",
        "location": "Bradford BD7",
        "url": "https://uk.indeed.com/company/Unique-Fitness,-University-of-Bradford/jobs/Sporting-Goods-Associate-efe14f97f610a0b2?fccid=08807156aeeb1bf6&vjs=3",
        "summary": "\nUndertake fitness tests, inductions and monitor individual training programmes.\nLevel 2 Fitness Instructor or requirement to achieve within first two months of\u2026\n",
        "creation_date": "PostedPosted 10 days ago",
        "saved_date": "2023-06-17"
    },
    {
        "name": "Kids Party - Outdoor Instructor",
        "company": "Kids on Quadz",
        "location": "Bognor Regis+1 location",
        "url": "https://uk.indeed.com/company/Kids-on-Quadz/jobs/Instructor-e690e3a74b580dee?fccid=e0c5579bc745acfc&vjs=3",
        "summary": "\nThis is a physically demanding job so overall fitness will be required.\nPay to be discussed depending on experience.\nPart-time hours: 20 per week.\n",
        "creation_date": "EmployerActive 3 days ago",
        "saved_date": "2023-06-17"
    },
    {
        "name": "Spin / Group Cycle Instructor",
        "company": "SB Leisure",
        "location": "Southampton",
        "url": "https://uk.indeed.com/company/SB-Leisure/jobs/Fitness-Instructor-ae4dab7aac3ea6e7?fccid=d1dc59ab1dfa0590&vjs=3",
        "summary": "\nThis is a part time role and would suit those working around school times.\nJob Types: Part-time, Permanent.\nPart-time hours: 5 per week.\n",
        "creation_date": "EmployerActive 5 days ago",
        "saved_date": "2023-06-17"
    },
    {
        "name": "Kids Quad Biking Party - Outdoor Instructor",
        "company": "Kids on Quadz",
        "location": "Bournemouth BH23",
        "url": "https://uk.indeed.com/company/Kids-on-Quadz/jobs/Instructor-6c488fd65bc4b576?fccid=e0c5579bc745acfc&vjs=3",
        "summary": "\nThis is a physically demanding job so overall fitness will be required.\nYour day-to-day role will include greeting families & children, getting them kitted up\u2026\n",
        "creation_date": "PostedPosted 1 day ago",
        "saved_date": "2023-06-17"
    },
    {
        "name": "Pilates Instructor",
        "company": "TruBe",
        "location": "Hammersmith and Fulham+4 locations",
        "url": "https://uk.indeed.com/company/TruBe/jobs/Pilates-Instructor-85fb469f18ba400e?fccid=fc5582771cde706e&vjs=3",
        "summary": "\nSuccessful candidates who gain entry on to the TruBe platform gain exposure to a wide range of fitness clients with various fitness goals.\n",
        "creation_date": "EmployerActive 9 days ago",
        "saved_date": "2023-06-17"
    },
    {
        "name": "Gym Instructor",
        "company": "Darwin Escapes",
        "location": "Pocklington YO42",
        "url": "https://uk.indeed.com/rc/clk?jk=1a92d25255c19290&fccid=4f17c53f8364c635&vjs=3",
        "summary": "\nCo-ordinate and deliver pre-planned fitness classes.\nWe are looking for someone with similar previous experience and a Level 2 Gym Instructor qualification.\n",
        "creation_date": "PostedToday",
        "saved_date": "2023-06-17"
    },
    {
        "name": "Swimming Instructor",
        "company": "Active Torridge",
        "location": "Northam",
        "url": "https://uk.indeed.com/company/Active-Torridge/jobs/Swim-Instructor-9bbde2568ca6dcf5?fccid=8b164aa3a7e57ec7&vjs=3",
        "summary": "\n1 additional day for all staff after 3 years service with Active Torridge.\nThe ideal candidate will have a Level 1 or 2 ASA or STA qualification and have\u2026\n",
        "creation_date": "EmployerActive 16 days ago",
        "saved_date": "2023-06-17"
    },
    {
        "name": "Class Instructor",
        "company": "Anytime Fitness Bath Central",
        "location": "Bath",
        "url": "https://uk.indeed.com/company/Anytime-Fitness-Bath-Central/jobs/Instructor-dd9c2328d355686a?fccid=cf2581fe8845e9be&vjs=3",
        "summary": "\nPersonal Training Certification to Level 3 or above (REPS).\nPart-time hours: 1-2 per week.\nWe have equipment ranging from cardiovascular to resistance and free\u2026\n",
        "creation_date": "PostedPosted 30+ days ago",
        "saved_date": "2023-06-17"
    },
    {
        "name": "Children\u2019s Martial Arts Instructor",
        "company": "Temple Martial Arts",
        "location": "Cambridge+2 locations",
        "url": "https://uk.indeed.com/company/RCACTIVE-Ltd/jobs/Martial-Arts-Instructor-a391a5314893347d?fccid=6690ad6fff5430ce&vjs=3",
        "summary": "\nA willingness to learn and develop as an instructor.\nThis role requires a personable individual who is passionate about working with children and can create\u2026\n",
        "creation_date": "EmployerActive 3 days ago",
        "saved_date": "2023-06-17"
    },
    {
        "name": "Boxing Coach - Boxercise",
        "company": "TruBe",
        "location": "Kensington and Chelsea+5 locations",
        "url": "https://uk.indeed.com/rc/clk?cmp=TruBe&ti=Boxing+Coach+-+Boxercise&jk=d899ad1e4eea8d52&fccid=fc5582771cde706e&vjs=3",
        "summary": "\nSuccessful candidates who gain entry on to the TruBe platform gain exposure to a wide range of fitness clients with various fitness goals.\n",
        "creation_date": "EmployerActive 3 days ago",
        "saved_date": "2023-06-17"
    },
    {
        "name": "Fitness Manager",
        "company": "Abbeycroft Leisure",
        "location": "Haverhill CB9",
        "url": "https://uk.indeed.com/company/Abbeycroft-Leisure/jobs/Fitness-Manager-6b781a05bfefa34c?fccid=8a1458617e702823&vjs=3",
        "summary": "\nThe centre offers swimming, gym, fitness classes, swimming lessons, health, and wellbeing classes plus a range of community programmes.\n",
        "creation_date": "EmployerActive 3 days ago",
        "saved_date": "2023-06-17"
    },
    {
        "name": "Instructor Demonstrator in Agriculture",
        "company": "Coleg Cambria",
        "location": "Rhuthun",
        "url": "https://uk.indeed.com/company/Coleg-Cambria/jobs/Demonstrator-71a7283a9108b958?fccid=add58cf1445fe86e&vjs=3",
        "summary": "\nQualified to a minimum of Level 3 or equivalent in a professionally relevant subject matter.\nCymhwyster Lefel 3 o leiaf neu gymhwyster cyfwerth mewn pwnc\u2026\n",
        "creation_date": "EmployerActive 3 days ago",
        "saved_date": "2023-06-17"
    },
    {
        "name": "Muay Thai or Kickboxing Instructor",
        "company": "Famfit Ltd (T/A Team Fighting Fit)",
        "location": "Leicester",
        "url": "https://uk.indeed.com/rc/clk?cmp=Famfit-Ltd-(T%2FA-Team-Fighting-Fit)&ti=Instructor&jk=d37980b5a4371ccf&fccid=0a6721dff7d07bc6&vjs=3",
        "summary": "\nIf you have level 3 PT then you'll have opportunities to work alongside our coaching team to train clients in general health and fitness too.\n",
        "creation_date": "EmployerActive 7 days ago",
        "saved_date": "2023-06-17"
    },
    {
        "name": "BODYPUMP Instructor",
        "company": "David Lloyd Clubs",
        "location": "Farnham GU9",
        "url": "https://uk.indeed.com/rc/clk?jk=d0f6b02d77a069bc&fccid=0df35c4fff829756&vjs=3",
        "summary": "\nHold a minimum of a current level 2 CIMSPA or exercise to music teaching qualification.\nAble to adapt a class to accommodate a wide range of ages and ability,\u2026\n",
        "creation_date": "PostedPosted 7 days ago",
        "saved_date": "2023-06-17"
    },
    {
        "name": "Pre and Postnatal Group Exercise Instructor",
        "company": "Firefly Fitness UK",
        "location": "London",
        "url": "https://uk.indeed.com/company/Firefly-Fitness-UK/jobs/Fitness-Instructor-0af6380ce4ee9db1?fccid=73ed56d86f4b4556&vjs=3",
        "summary": "\nDemonstrate sound knowledge in pre and postnatal fitness.\nOur organisation is looking for a pre and postnatal and group instructor qualified candidate with a\u2026\n",
        "creation_date": "EmployerActive 8 days ago",
        "saved_date": "2023-06-17"
    },
    {
        "name": "Children's Activities Instructor & Coordinator",
        "company": "China Fleet Country Club Ltd",
        "location": "Saltash PL12",
        "url": "https://uk.indeed.com/company/ChinaFleet-Country-Club/jobs/Activities-Director-3179dead463cde5a?fccid=a811453d299f44e0&vjs=3",
        "summary": "\nLeading & managing a group of children with enthusiasm & control.\nDesigning & progressing an engaging children\u2019s activity timetable for both the school term\u2026\n",
        "creation_date": "EmployerActive 4 days ago",
        "saved_date": "2023-06-17"
    },
    {
        "name": "Aqua Aerobic Instructor",
        "company": "SB Leisure",
        "location": "Southampton",
        "url": "https://uk.indeed.com/company/SB-Leisure/jobs/Instructor-ba39dbe6721d9f97?fccid=d1dc59ab1dfa0590&vjs=3",
        "summary": "\nWe currently run aqua aerobics daily for our customers and we are looking for someone either experienced that can slot right in or someone willing to learn from\u2026\n",
        "creation_date": "EmployerActive 5 days ago",
        "saved_date": "2023-06-17"
    },
    {
        "name": "Aqua Class Instructor",
        "company": "Chilworth Manor Hotel",
        "location": "Southampton SO16",
        "url": "https://uk.indeed.com/company/Best-Western/jobs/Instructor-c4f6c809056517b8?fccid=aa8d757d495cf43c&vjs=3",
        "summary": "\nYou have at least an NVQ Level 2 in Fitness or Aqua and an Aqua instructor qualification.\nYou check in with the club team often and always keep up to date with\u2026\n",
        "creation_date": "EmployerActive 4 days ago",
        "saved_date": "2023-06-17"
    },
    {
        "name": "Outdoor Activity Instructor Apprenticeship - Dearne Valley - September 2023",
        "company": "Kingswood",
        "location": "Doncaster DN12+8 locations",
        "url": "https://uk.indeed.com/rc/clk?jk=0eea029f1417ed8d&fccid=8da1da53ba6920d0&vjs=3",
        "summary": "\nQualification type: Advanced Level Apprenticeship Level 3.\nEnglish GCSE at level 3 or grade D.\nCommunication skills, Attention to detail, Organisation skills,\u2026\n",
        "creation_date": "PostedPosted 2 days ago",
        "saved_date": "2023-06-17"
    },
    {
        "name": "Pilates Instructor",
        "company": "Anytime Fitness Dalston",
        "location": "London",
        "url": "https://uk.indeed.com/company/Anytime-Fitness-Dalston/jobs/Pilates-Instructor-64a940da70e7338d?fccid=09c91b6a3400e5c5&vjs=3",
        "summary": "\nAnytime Fitness Dalston is looking for a reliable and amazing Pilates instructor for Tuesday at 6.30 pm!*.\nDepending upon the individual there may be further\u2026\n",
        "creation_date": "EmployerActive 17 days ago",
        "saved_date": "2023-06-17"
    },
    {
        "name": "Boogie Bounce Instructor",
        "company": "Fitness Fairy",
        "location": "Southampton",
        "url": "https://uk.indeed.com/company/Fitness-Fairy/jobs/Instructor-0d1c6995d79aae3c?fccid=f3c34bfabfd4610f&vjs=3",
        "summary": "\nPart-time hours: 1-3 per week.\nYou will be the heart and soul of our business and usually the only face our customers see, so we provide you with adequate\u2026\n",
        "creation_date": "EmployerActive 4 days ago",
        "saved_date": "2023-06-17"
    },
    {
        "name": "Group Exercise Instructor \u2013 BLAZE",
        "company": "David Lloyd Clubs",
        "location": "London SW6+1 location",
        "url": "https://uk.indeed.com/rc/clk?jk=b88fb63bbcb90e67&fccid=0df35c4fff829756&vjs=3",
        "summary": "\nOur expectations are that classes must be safe, well attended and professionally taught and that our members always leave your class having had an amazing\u2026\n",
        "creation_date": "PostedPosted 7 days ago",
        "saved_date": "2023-06-17"
    },
    {
        "name": "Studio Instructor - Casual - Nene Leisure Centre",
        "company": "Freedom Leisure",
        "location": "Thrapston NN14+1 location",
        "url": "https://uk.indeed.com/rc/clk?jk=f29361ca3c6838b4&fccid=b7fc9a95cd7d047c&vjs=3",
        "summary": "\nRewarding role supporting health & fitness in the community.\nNationally recognised group exercise qualification.\n",
        "creation_date": "PostedToday",
        "saved_date": "2023-06-17"
    },
    {
        "name": "Studio Based Class Instructor - Everlast Gyms",
        "company": "Everlast Gyms",
        "location": "Barnsley S71+2 locations",
        "url": "https://uk.indeed.com/rc/clk?jk=f128a5f4414d52e9&fccid=cb1cd90c3b82c316&vjs=3",
        "summary": "\nWe are looking for level 2 qualified instructors who are able to use their own unique teaching style to teach resistance-based classes, bootcamps, circuit\u2026\n",
        "creation_date": "PostedPosted 30+ days ago",
        "saved_date": "2023-06-17"
    },
    {
        "name": "Aqua Zumba Instructor",
        "company": "Everyone Active",
        "location": "North Walsham NR28",
        "url": "https://uk.indeed.com/company/Everyone-Active/jobs/Fitness-Instructor-a11828b51f3e6804?fccid=0b7134f5982ee145&vjs=3",
        "summary": "\nThe successful candidate will be responsible for planning and providing fitness instruction in aqua classes for our customers to a high standard*.\n",
        "creation_date": "PostedPosted 11 days ago",
        "saved_date": "2023-06-17"
    },
    {
        "name": "Membership Advisor/Gym Instructor",
        "company": "Anytime Fitness Woolwich",
        "location": "London SE18",
        "url": "https://uk.indeed.com/company/Anytime-Fitness/jobs/Membership-Representative-b19fd54f282a6557?fccid=fa9944eac2718763&vjs=3",
        "summary": "\nDeliver gym based exercise classes, Membership's sales, dealing with enquiries and customer retention.\nDelivering engaging and effective gym appointments both 1\u2026\n",
        "creation_date": "EmployerActive 1 day ago",
        "saved_date": "2023-06-17"
    },
    {
        "name": "Reformer Pilates Instructor",
        "company": "Tempo 301",
        "location": "London E1",
        "url": "https://uk.indeed.com/company/Tempo-Pilates/jobs/Pilates-Instructor-6da0ebe81b8ea28f?fccid=b6e8641058059525&vjs=3",
        "summary": "\n3 to 5 consecutive hours per shift and schedule consistency.\nPart-time hours: 3 per week.\nCurrent availability is Saturdays 11 am until 2 pm from 22nd of April\u2026\n",
        "creation_date": "EmployerActive 10 days ago",
        "saved_date": "2023-06-17"
    },
    {
        "name": "Fitness Class Co-Ordinator",
        "company": "On1Fitness",
        "location": "Morden",
        "url": "https://uk.indeed.com/company/On1Fitness/jobs/Production-Coordinator-2594e3ec8c5fd9d3?fccid=5750da4f9d064fde&vjs=3",
        "summary": "\nA level 3 personal training qualification.\nA qualified instructor with the relevant credentials in group-based exercise.\nPart-time hours: 12-16 per week.\n",
        "creation_date": "PostedPosted 30+ days ago",
        "saved_date": "2023-06-17"
    },
    {
        "name": "Martial Arts Trainer",
        "company": "AG Martial Arts",
        "location": "Salisbury",
        "url": "https://uk.indeed.com/company/AG-Martial-Arts/jobs/Martial-Arts-Instructor-f6f8e68cba54cf66?fccid=ec0586c9ac197e3e&vjs=3",
        "summary": "\nProviding high quality, engaging martial arts instruction to students of all ages and levels.\nPreparing lesson plans that align with our curriculum and guide\u2026\n",
        "creation_date": "PostedPosted 1 day ago",
        "saved_date": "2023-06-17"
    },
    {
        "name": "Group Cycle Instructor - Rhythm",
        "company": "David Lloyd Clubs",
        "location": "Woking GU22",
        "url": "https://uk.indeed.com/rc/clk?jk=0553b9f9860194ae&fccid=0df35c4fff829756&vjs=3",
        "summary": "\nHold a minimum of a current level 2 CIMSPA or Level 2 exercise to music teaching qualification or equivalent outdoor cycling qualification.\n",
        "creation_date": "PostedPosted 8 days ago",
        "saved_date": "2023-06-17"
    },
    {
        "name": "Spin Instructor - Everlast Gyms",
        "company": "Everlast Gyms",
        "location": "Barnsley S71+1 location",
        "url": "https://uk.indeed.com/rc/clk?jk=cf2cd3b444c2182a&fccid=cb1cd90c3b82c316&vjs=3",
        "summary": "\nYou always keep up to date with class policies and instructor procedures.\nOur expectations are that classes must be safe & effective, well attended and\u2026\n",
        "creation_date": "PostedPosted 30+ days ago",
        "saved_date": "2023-06-17"
    },
    {
        "name": "Holiday Camp Coordinator",
        "company": "Greenbank Sports Academy",
        "location": "Liverpool L17",
        "url": "https://uk.indeed.com/company/Greenbank-Sports-Academy/jobs/Camp-Manager-94c18d4d56789c38?fccid=0d441e13c6810ff8&vjs=3",
        "summary": "\nA recognized playworker or equivalent instructor qualification, and educated to A-level or equivalent.\nAll employees are required to be flexible in their\u2026\n",
        "creation_date": "PostedPosted 1 day ago",
        "saved_date": "2023-06-17"
    },
    {
        "name": "Bank - Instructor - YMCA St Annes",
        "company": "YMCA Fylde Coast",
        "location": "Lytham St. Annes FY8",
        "url": "https://uk.indeed.com/company/YMCA/jobs/Instructor-822740c385eef2a7?fccid=cff6c2b12d7dc183&vjs=3",
        "summary": "\nSupport members in achieving their fitness goals.\nWe offer flexible working, with an emphasis on learning and development through our online training portal for\u2026\n",
        "creation_date": "EmployerActive 3 days ago",
        "saved_date": "2023-06-17"
    },
    {
        "name": "Instructor Strategy Coordinator (Fixed Term Contract)",
        "company": "Peloton",
        "location": "London",
        "url": "https://uk.indeed.com/rc/clk?jk=363e0717eacc3b1d&fccid=8899ecbdba2d0a5e&vjs=3",
        "summary": "\nPeloton provides Members with expert instruction, world-class content and the fitness industry's leading music library to create impactful and entertaining\u2026\n",
        "creation_date": "PostedPosted 30 days ago",
        "saved_date": "2023-06-17"
    },
    {
        "name": "General Manager",
        "company": "JD Gyms",
        "location": "Wirral",
        "url": "https://uk.indeed.com/company/JD-Gyms/jobs/General-Manager-7afa97cfbcdead25?fccid=0b6f16690b47cff8&vjs=3",
        "summary": "\nLevel 2 fitness instructor qualification (required).\nMust be qualified to at least Level 2 Gym Instructor.\nGym management: 2 years (required).\n",
        "creation_date": "EmployerActive 17 days ago",
        "saved_date": "2023-06-17"
    },
    {
        "name": "GP referral/ Wellbeing Instructor",
        "company": "Leisure Focus Trust",
        "location": "Maidenhead SL6",
        "url": "https://uk.indeed.com/company/Leisure-Focus-Trust/jobs/General-Practitioner-e472e5439ee6a218?fccid=b50fcc743b8ee2a3&vjs=3",
        "summary": "\nNEST Auto Enrolment after 3 months service.\nFree gym membership for the employee and appointed person.\nIf you have a genuine passion for supporting people, join\u2026\n",
        "creation_date": "EmployerActive 5 days ago",
        "saved_date": "2023-06-17"
    },
    {
        "name": "Activity Instructor",
        "company": "South West Lakes Trust",
        "location": "Lifton",
        "url": "https://uk.indeed.com/company/South-West-Lakes-Trust/jobs/Instructor-718676c406798775?fccid=c57addf37f9d63ca&vjs=3",
        "summary": "\n4.2 A good level of physical fitness.\nASI / BSUPA / BC paddleboarding instructor.\n1.4 HOURS 40 hrs per week, to include weekends, evenings.\n",
        "creation_date": "EmployerActive 4 days ago",
        "saved_date": "2023-06-17"
    },
    {
        "name": "Health and Fitness Advisor",
        "company": "Live Borders",
        "location": "Selkirk",
        "url": "https://uk.indeed.com/company/Live-Borders/jobs/Fitness-Consultant-790efe7f108d5d2a?fccid=a1d861f9ad360249&vjs=3",
        "summary": "\nDeliver high quality fitness classes as and when required to satisfy the needs of the membership.\nImprove member retention by increasing the number and quality\u2026\n",
        "creation_date": "EmployerActive 3 days ago",
        "saved_date": "2023-06-17"
    },
    {
        "name": "Swimming Instructor",
        "company": "David Lloyd Clubs",
        "location": "Norwich NR6+7 locations",
        "url": "https://uk.indeed.com/rc/clk?jk=d2ddd754660ce813&fccid=0df35c4fff829756&vjs=3",
        "summary": "\nFull club membership for you and another family member / friend.\n50% off food and drink.\nTraining and development opportunities including sports massage\u2026\n",
        "creation_date": "PostedPosted 7 days ago",
        "saved_date": "2023-06-17"
    },
    {
        "name": "Swimming Instructor - Crescent Link",
        "company": "H2o Swimming Academy",
        "location": "Derry",
        "url": "https://uk.indeed.com/company/H2o-Swimming-Academy/jobs/Swim-Instructor-59b837681da4b38d?fccid=b8bb39f65dbab7e7&vjs=3",
        "summary": "\nLevel 2 Swim England/ASA or STA Certificate Qualification or equivalent.\nLevel 2 swim teacher qualification (required).\nPart-time hours: 19 per week.\n",
        "creation_date": "EmployerActive 3 days ago",
        "saved_date": "2023-06-17"
    },
    {
        "name": "Reformer Pilates Instructor",
        "company": "Urban Pilates",
        "location": "London",
        "url": "https://uk.indeed.com/company/Urban-Pilates/jobs/Pilates-Instructor-95038c2bd2af3aa7?fccid=4f16a81f9a3eb5d4&vjs=3",
        "summary": "\nLevel 2/3 Certificate in Pilates Reformer and equipment or equivalent.\nJOB FUNCTION: To provide a welcoming atmosphere for all guests and members, supporting\u2026\n",
        "creation_date": "PostedPosted 30+ days ago",
        "saved_date": "2023-06-17"
    },
    {
        "name": "Sales & Fitness Consultant",
        "company": "Energie Fitness Pontypridd",
        "location": "Pontypridd",
        "url": "https://uk.indeed.com/company/Energie-Fitness-Pontypridd/jobs/Fitness-Consultant-e650feb09634d136?fccid=b881030a88cc8014&vjs=3",
        "summary": "\nLevel 2 class instructor certificate (preferred).\nTo ensure customers/members have a 5 star experience when in club.\nPart-time hours: 14 per week.\n",
        "creation_date": "EmployerActive 3 days ago",
        "saved_date": "2023-06-17"
    },
    {
        "name": "General Manager",
        "company": "Club Pilates United Kingdom",
        "location": "London SE1",
        "url": "https://uk.indeed.com/company/Club-Pilates-United-Kingdom/jobs/General-Manager-d40af34615b7b1c8?fccid=f7a1ac5575bf7f05&vjs=3",
        "summary": "\nReview instructor evaluations performed by Master Trainers.\nHire/Manage all instructors at the studio.\nThe ideal Manager will oversee all Studio functionality\u2026\n",
        "creation_date": "EmployerActive 3 days ago",
        "saved_date": "2023-06-17"
    },
    {
        "name": "Horse Riding Instructor",
        "company": "Cumbria Rural Academy CIC at Bigland Hall",
        "location": "Ulverston",
        "url": "https://uk.indeed.com/company/Cumbria-rural-academy-at-Bigland-Hall/jobs/Equestrian-Coach-cceb02f77bcc2f62?fccid=6f257215efea3b99&vjs=3",
        "summary": "\n_Harness Change at Cumbria Rural Academy CIC provides educational courses and training to promote fitness, physical and emotional wellbeing, as well as\u2026\n",
        "creation_date": "EmployerActive 3 days ago",
        "saved_date": "2023-06-17"
    },
    {
        "name": "Pilates Mat 3 Instructor Birmingham",
        "company": "VIPilates",
        "location": "Birmingham",
        "url": "https://uk.indeed.com/company/ViPilates/jobs/Pilates-Instructor-a1706f206014a146?fccid=f834a5d1c6949a71&vjs=3",
        "summary": "\nSarah believes that Pilates can help heal your body, and connect your mind to your body, no matter the age, body type or fitness level.\n",
        "creation_date": "PostedPosted 30+ days ago",
        "saved_date": "2023-06-17"
    },
    {
        "name": "Specialist Intervention Lead Instructor",
        "company": "Essex Police, Fire and Crime Commissioner Fire and...",
        "location": "Witham CM8",
        "url": "https://uk.indeed.com/company/Essex-County-Fire-&-Rescue-Services/jobs/Lead-Instructor-c4ad48d09ce98899?fccid=1af9382395392f80&vjs=3",
        "summary": "\n> You must have a valid and current FiTech of 42 VO2 max, or be actively engaged in a programme of fitness.\nThere are requirements to travel within and outside\u2026\n",
        "creation_date": "PostedPosted 30+ days ago",
        "saved_date": "2023-06-17"
    },
    {
        "name": "Swimming Instructor (Qualified).",
        "company": "GLL",
        "location": "Ruislip HA4",
        "url": "https://uk.indeed.com/company/GLL/jobs/Swim-Instructor-ed0a3b98231adf33?fccid=4b4c2ac64a4ed95e&vjs=3",
        "summary": "\nJob Types: Full-time, Part-time, Permanent, Zero hours contract.\nPart-time hours: 4-24 per week.\n",
        "creation_date": "EmployerActive 10 days ago",
        "saved_date": "2023-06-17"
    },
    {
        "name": "Group Exercise - Master Trainer (Maternity Cover)",
        "company": "Life Leisure",
        "location": "Stockport",
        "url": "https://uk.indeed.com/company/Life-Leisure/jobs/Fitness-Instructor-3aac84b23dff12e2?fccid=1e9219d0091074fa&vjs=3",
        "summary": "\nSkills: Minimum REPS Level 3 (Les Mills Quals Preferred).\nTeaching group ex: 2 years (required).\nThe role will be 16 hours per week of concept and instructor\u2026\n",
        "creation_date": "EmployerActive 3 days ago",
        "saved_date": "2023-06-17"
    },
    {
        "name": "Swim Instructor",
        "company": "Kings Fitness and Leisure",
        "location": "Cheddar",
        "url": "https://uk.indeed.com/company/Kings-Fitness-&-Leisure/jobs/Swim-Instructor-5f4206025ff10f28?fccid=c2bebf41f7bb2d3e&vjs=3",
        "summary": "\nThe Swim School at Kings Fitness & Leisure runs for 50 weeks of the year, with no swimming taking place for the 2 weeks over Christmas.\n",
        "creation_date": "EmployerActive 6 days ago",
        "saved_date": "2023-06-17"
    },
    {
        "name": "Aqua Aerobics Instructor",
        "company": "Everyone Active",
        "location": "Solihull",
        "url": "https://uk.indeed.com/company/Everyone-Active/jobs/Instructor-4bfc091fb53505b6?fccid=0b7134f5982ee145&vjs=3",
        "summary": "\nThe successful candidate will be responsible for planning and providing fitness instruction in aqua classes for our customers to a high standard*.\n",
        "creation_date": "PostedPosted 15 days ago",
        "saved_date": "2023-06-17"
    },
    {
        "name": "Gym Manager",
        "company": "The Engine Room",
        "location": "London NW1",
        "url": "https://uk.indeed.com/company/Shaping-Change-Ltd/jobs/Fitness-Manager-aadb482f304404b3?fccid=d825b2546e737c63&vjs=3",
        "summary": "\nManage the staff of fitness instructors and personal trainers.\nDevelop and implement fitness programs for members.\nDirect sales: 2 years (preferred).\n",
        "creation_date": "PostedPosted 2 days ago",
        "saved_date": "2023-06-17"
    },
    {
        "name": "Swimming Instructor - Nottingham",
        "company": "H2o Swimming Academy",
        "location": "Nottingham NG4+4 locations",
        "url": "https://uk.indeed.com/company/H2o-Swimming-Academy/jobs/Swim-Instructor-5443d6723edf74ad?fccid=b8bb39f65dbab7e7&vjs=3",
        "summary": "\nLevel 2 Swim England/ASA or STA Certificate Qualification or equivalent.\nCover hours also available on adhoc basis.\nJob Types: Part-time, Permanent.\n",
        "creation_date": "EmployerActive 4 days ago",
        "saved_date": "2023-06-17"
    },
    {
        "name": "Spin Instructor (Cover)",
        "company": "Snap Fitness Trowbridge",
        "location": "Trowbridge BA14",
        "url": "https://uk.indeed.com/company/Snap-Fitness/jobs/Instructor-2164e252fc8b72a8?fccid=c89f100a57d84248&vjs=3",
        "summary": "\nSnap Fitness Trowbridge are currently looking for 2 new Fitness Instructors to join their team.\nWe will be looking for Instructors to run engaging classes at\u2026\n",
        "creation_date": "EmployerActive 4 days ago",
        "saved_date": "2023-06-17"
    },
    {
        "name": "Freelance Swimming Instructor",
        "company": "The Tytherington Club",
        "location": "Macclesfield SK10",
        "url": "https://uk.indeed.com/company/The-Club-Company/jobs/Swim-Instructor-64622e7a29c4ae30?fccid=633c46ea277ac967&vjs=3",
        "summary": "Freelance Self employed Swimming Instructor The Club Company's mission is to be unquestionably the UK's premier collection of country clubs and we understand\u2026",
        "creation_date": "PostedPosted 3 days ago",
        "saved_date": "2023-06-17"
    },
    {
        "name": "Parent & Toddler Swim Instructor",
        "company": "Mosaic Spa & Health Clubs",
        "location": "Portsmouth PO3",
        "url": "https://uk.indeed.com/company/Mosaic-Spa-&-Health-Clubs/jobs/Swim-Instructor-52e8966e7d775e4e?fccid=49bb0fd7e1ba4ac7&vjs=3",
        "summary": "\nPart-time hours: 4 per week.\nParent & Toddler Swimming Teacher Qualification (required).\n",
        "creation_date": "EmployerActive 4 days ago",
        "saved_date": "2023-06-17"
    },
    {
        "name": "Group Cycling Instructor",
        "company": "David Lloyd Clubs",
        "location": "Dundee DD5",
        "url": "https://uk.indeed.com/rc/clk?jk=3e498f9c3b7807e3&fccid=0df35c4fff829756&vjs=3",
        "summary": "About the Role Come and ride with us... Indoor Cycling Instructors needed! We are looking for awesome performers, dancers, athletes, instructors with\u2026",
        "creation_date": "PostedPosted 3 days ago",
        "saved_date": "2023-06-17"
    },
    {
        "name": "Multi Sports Coach",
        "company": "Changing Lives Community Services",
        "location": "Harlow",
        "url": "https://uk.indeed.com/company/Changing-Lives-Community-Services/jobs/Sports-Coach-a6e2b4b6f50ab88f?fccid=e0eb483637b5798f&vjs=3",
        "summary": "\nDelivering a variety of sports and physical activity sessions to groups of up to 20 children;\nEncouraging children to engage and have fun during sessions;\n",
        "creation_date": "EmployerActive 4 days ago",
        "saved_date": "2023-06-17"
    },
    {
        "name": "Group Exercise Manager",
        "company": "Third Space - Wimbledon",
        "location": "London SW19",
        "url": "https://uk.indeed.com/rc/clk?jk=ceb8c9746565263b&fccid=6ab11fb8bd4bab1b&vjs=3",
        "summary": "\nThe successful candidate will also need to hold workshops and coaching sessions for internal team members, such as the sales and fitness team, so that the\u2026\n",
        "creation_date": "PostedPosted 1 day ago",
        "saved_date": "2023-06-17"
    },
    {
        "name": "Gym Instructor/Membership Advisor",
        "company": "Anytime Fitness",
        "location": "Colindale",
        "url": "https://uk.indeed.com/company/Dileva-Fitness-Ltd/jobs/Membership-Representative-3567acff9d8c5a6e?fccid=36989ded9ebc0d75&vjs=3",
        "summary": "\nBe qualified to a minimum of level 2 and 3 - With experience in delivering group fitness classes.\nLevel 3 Personal Training certificate (required).\n",
        "creation_date": "EmployerActive 3 days ago",
        "saved_date": "2023-06-17"
    },
    {
        "name": "Swimming Instructor (self employed)",
        "company": "David Lloyd Clubs",
        "location": "Coventry CV3+9 locations",
        "url": "https://uk.indeed.com/rc/clk?jk=fa434ec2a8aa0e51&fccid=0df35c4fff829756&vjs=3",
        "summary": "\nHave strong engagement, good communication and active listening skills.\n",
        "creation_date": "PostedPosted 1 day ago",
        "saved_date": "2023-06-17"
    },
    {
        "name": "Fitness & Pilates Studio Manager",
        "company": "MOHIITO",
        "location": "Hybrid remote in Bristol BS6",
        "url": "https://uk.indeed.com/company/MOHIITO/jobs/Studio-Manager-22a32f60343d99a1?fccid=3148f41b69de8834&vjs=3",
        "summary": "\nYou will be required to determine your working schedule and coordinate with your virtual support assistant and instructors each week to ensure that there is\u2026\n",
        "creation_date": "EmployerActive 5 days ago",
        "saved_date": "2023-06-17"
    },
    {
        "name": "Group Cycling Instructor",
        "company": "Everyone Active",
        "location": "Uttoxeter ST14",
        "url": "https://uk.indeed.com/company/Everyone-Active/jobs/Instructor-d04c0c657481bc8d?fccid=0b7134f5982ee145&vjs=3",
        "summary": "\nThe successful candidate will be responsible for planning and providing fitness instruction in group cycling classes for our customers to a high standard.*.\n",
        "creation_date": "PostedPosted 9 days ago",
        "saved_date": "2023-06-17"
    },
    {
        "name": "Teacher / Instructor of Social Emotional and Mental Health Difficulties",
        "company": "Now Education",
        "location": "Walsall",
        "url": "https://uk.indeed.com/company/Now-Education/jobs/Mental-Health-Technician-6dcc54f9438c29ce?fccid=cd14588072df0a4a&vjs=3",
        "summary": "\nThe position would entail general delivery across a variety of subjects in Key Stage 3.\nAll applicants will be required to provide two suitable references to\u2026\n",
        "creation_date": "PostedPosted 30+ days ago",
        "saved_date": "2023-06-17"
    },
    {
        "name": "SPIN INSTRUCTOR",
        "company": "Sheaf House Farm",
        "location": "Blockley GL56+1 location",
        "url": "https://uk.indeed.com/company/Freestyle360/jobs/Instructor-5964f86265466fb1?fccid=a60809b3581e1089&vjs=3",
        "summary": "\nOur spin sessions run through the week in the morning and evening, including Saturday mornings.\nSPIN INSTRUCTOR: 1 year (preferred).\n",
        "creation_date": "PostedPosted 30+ days ago",
        "saved_date": "2023-06-17"
    },
    {
        "name": "Pilates Instructor",
        "company": "Snap Fitness Tonbridge",
        "location": "Tonbridge TN9",
        "url": "https://uk.indeed.com/company/Snap-Fitness/jobs/Pilates-Instructor-8bb527abf79d12e1?fccid=c89f100a57d84248&vjs=3",
        "summary": "\nWhether customers come to lose weight or get fitter, your classes will help everyone to build confidence as well as fitness.\nPart-time hours: 1-4 per week.\n",
        "creation_date": "EmployerActive 9 days ago",
        "saved_date": "2023-06-17"
    },
    {
        "name": "Level 2 Swimming Teacher",
        "company": "Wales National Pool Swansea",
        "location": "Swansea",
        "url": "https://uk.indeed.com/company/Wales-National-Pool-Swansea/jobs/Swim-Instructor-32c8682d0c7f16cd?fccid=28afb6e2750b8811&vjs=3",
        "summary": "\nDemonstrate a strong commitment to Customer Care.\nGood interpersonal skills with ability to develop and sustain relationships with a wide variety of people both\u2026\n",
        "creation_date": "PostedToday",
        "saved_date": "2023-06-17"
    },
    {
        "name": "Self Employed Swimming Instructor",
        "company": "David Lloyd Clubs",
        "location": "West Malling",
        "url": "https://uk.indeed.com/company/David-Lloyd-Clubs/jobs/Swim-Instructor-5dc6a2b59ff02956?fccid=0df35c4fff829756&vjs=3",
        "summary": "\nHave strong engagement, good communication and active listening skills.\nPart-time hours: 8 per week.\nWest Malling: reliably commute or plan to relocate before\u2026\n",
        "creation_date": "EmployerActive 19 days ago",
        "saved_date": "2023-06-17"
    },
    {
        "name": "Swimming Teacher",
        "company": "Inspiring healthy lifestyles",
        "location": "Selby YO8",
        "url": "https://uk.indeed.com/company/Inspiring-healthy-lifestyles/jobs/Swim-Instructor-bdf2d1b05dba4b72?fccid=6be17bfde23afae1&vjs=3",
        "summary": "\nPrepare, plan, and deliver a varied and exciting range of lessons to all ages.\nAssess the skills of our swimmers and report back to parents.\n",
        "creation_date": "EmployerActive 3 days ago",
        "saved_date": "2023-06-17"
    },
    {
        "name": "Instructor - Agricultural Engineering (Further Education)",
        "company": "Hartpury University and College",
        "location": "Gloucester GL19",
        "url": "https://uk.indeed.com/rc/clk?jk=3a5785d8b8032c89&fccid=ac048b425b86f75b&vjs=3",
        "summary": "\n37.5 hours per week / Term time only, over 5 days per week, also available.\nSupport Lecturers in the delivery of Machinery/Workshop practical based units.\n",
        "creation_date": "PostedPosted 30+ days ago",
        "saved_date": "2023-06-17"
    },
    {
        "name": "Group Exercise Manager - New Club Opening",
        "company": "Leisure People Recruitment",
        "location": "Wimbledon",
        "url": "https://uk.indeed.com/company/Leisure-People-Recruitment/jobs/Group-Manager-b3dbcff998a8e980?fccid=6a10f569b7615ccd&vjs=3",
        "summary": "\nYou will play a pivotal role in the attraction, recruitment and ongoing management of your instructor team and ensuring their ongoing commitment to their\u2026\n",
        "creation_date": "PostedPosted 6 days ago",
        "saved_date": "2023-06-17"
    },
    {
        "name": "Level 2 Gym Instructor",
        "company": "SB Fitness",
        "location": "Broadstone",
        "url": "https://uk.indeed.com/company/SBFitness/jobs/Instructor-a2fbfc461558fb10?fccid=0b153873128984ad&vjs=3",
        "summary": "\nAt our main delivery site in Broadstone, Poole (BH18 8AX) we are currently looking for a confident, hardworking and reliable individual to join us as a part\u2026\n",
        "creation_date": "EmployerActive 3 days ago",
        "saved_date": "2023-06-17"
    },
    {
        "name": "Gymnastics and Trampolining Coaches - Qualified and Unqualified positions",
        "company": "UK Academies of Gymnastics - Tidworth Gymnastics...",
        "location": "Tidworth SP9",
        "url": "https://uk.indeed.com/company/UK-Academies-of-Gymnastics---Totton-Gymnastics-Academy/jobs/Gymnastics-Coach-b0f4940c3a268475?fccid=3a3a43367e45f57e&vjs=3",
        "summary": "\nExperience of delivering sports, health or fitness programs.\nUKAG Gymnastics & Trampolining Coaching Level 2 Certificate for Level 1 Coaches and Teachers*.\n",
        "creation_date": "EmployerActive 3 days ago",
        "saved_date": "2023-06-17"
    },
    {
        "name": "Leisure Attendant",
        "company": "Mercure Shrewsbury Albrighton Hall Hotel & Spa",
        "location": "Shrewsbury SY4",
        "url": "https://uk.indeed.com/company/Accor/jobs/Leisure-Attendant-4055763d759c4213?fccid=e52a8045d312f049&vjs=3",
        "summary": "\nLevel 2 gym instructor qualification - desirable .\nLevel 3 gym qualification - Desirable.\nLevel 3 Pool Plant operator - Desirable.\n",
        "creation_date": "EmployerActive 3 days ago",
        "saved_date": "2023-06-17"
    },
    {
        "name": "Digital Group Exercise Master Trainer",
        "company": "Johnson Health Tech Digital",
        "location": "High Wycombe",
        "url": "https://uk.indeed.com/company/Johnson-Health-Tech/jobs/Fitness-Instructor-089b0445ea6a1fee?fccid=be5344ad7b3c8b15&vjs=3",
        "summary": "\nTo have a passionate commitment to the social side of Group Exercise, for example by hosting regular live events at the GX Hub.\n",
        "creation_date": "EmployerActive 4 days ago",
        "saved_date": "2023-06-17"
    },
    {
        "name": "Pilates Instructor",
        "company": "Everyone Active",
        "location": "Winchester",
        "url": "https://uk.indeed.com/company/Everyone-Active/jobs/Pilates-Instructor-9ed217f4db4211a7?fccid=0b7134f5982ee145&vjs=3",
        "summary": "\nThe successful candidate will be responsible for planning and providing fitness instruction in Pilates classes for our customers to a high standard*.\n",
        "creation_date": "PostedPosted 24 days ago",
        "saved_date": "2023-06-17"
    },
    {
        "name": "Gymnastics and Trampolining Coaches - Qualified and Unqualified positions",
        "company": "UK Academies of Gymnastics - Ashbourne Gymnastics...",
        "location": "Ashbourne DE6",
        "url": "https://uk.indeed.com/company/UK-Academies-of-Gymnastics---Totton-Gymnastics-Academy/jobs/Gymnastics-Coach-0d48ae2dd107e1b3?fccid=3a3a43367e45f57e&vjs=3",
        "summary": "\nExperience of delivering sports, health or fitness programs.\nUKAG Gymnastics & Trampolining Coaching Level 2 Certificate for Level 1 Coaches and Teachers*.\n",
        "creation_date": "EmployerActive 3 days ago",
        "saved_date": "2023-06-17"
    },
    {
        "name": "Aqua Aerobics",
        "company": "David Lloyd Clubs",
        "location": "Hounslow TW5+1 location",
        "url": "https://uk.indeed.com/rc/clk?jk=7cb5f5bccf2b6df1&fccid=0df35c4fff829756&vjs=3",
        "summary": "\nHold a minimum of a current level 2 CIMSPA or exercise to music teaching qualification.\nHold a minimum Level 2 In water-based exercise.\n",
        "creation_date": "PostedPosted 25 days ago",
        "saved_date": "2023-06-17"
    },
    {
        "name": "Club Manager *(Sales & Operations)",
        "company": "Lifestyle Fitness",
        "location": "Ewell",
        "url": "https://uk.indeed.com/company/Lifestyle-Fitness-(UK)/jobs/Club-Manager-0e1a9dd887f41874?fccid=9437beef7d6316d7&vjs=3",
        "summary": "\nWork in a similar health and fitness environment.\nYou will be responsible for maintaining the high standards of the Club and customer service excellence.\n",
        "creation_date": "EmployerActive 3 days ago",
        "saved_date": "2023-06-17"
    },
    {
        "name": "Level 2 Gym Instructor (Self-Employed)",
        "company": "Fit Bodies Gym & Fitness",
        "location": "Leek ST13",
        "url": "https://uk.indeed.com/company/Fit-Bodies-Gym-&-Fitness/jobs/Instructor-8765dbb201efeb01?fccid=72e5ebcfb169c534&vjs=3",
        "summary": "\nLevel 2 Gym Instructor Qualification (preferred).\nYou will be creating fantastic relationships with our members & running the gym floor on a day-to-day basis.\n",
        "creation_date": "EmployerActive 8 days ago",
        "saved_date": "2023-06-17"
    },
    {
        "name": "Gymnastics and Trampolining Coaches - Qualified and Unqualified positions",
        "company": "UK Academies of Gymnastics - Salisbury Gymnastics...",
        "location": "Salisbury",
        "url": "https://uk.indeed.com/company/UK-Academies-of-Gymnastics---Totton-Gymnastics-Academy/jobs/Gymnastics-Coach-c8643b93868f03af?fccid=3a3a43367e45f57e&vjs=3",
        "summary": "\nExperience of delivering sports, health or fitness programs.\nUKAG Gymnastics & Trampolining Coaching Level 2 Certificate for Level 1 Coaches and Teachers*.\n",
        "creation_date": "EmployerActive 3 days ago",
        "saved_date": "2023-06-17"
    },
    {
        "name": "Gymnastics and Trampolining Coaches - Qualified and Unqualified positions",
        "company": "UK Academies of Gymnastics - Yeovil Gymnastics...",
        "location": "Yeovil BA20",
        "url": "https://uk.indeed.com/company/UK-Academies-of-Gymnastics---Totton-Gymnastics-Academy/jobs/Gymnastics-Coach-d114dab13a4fd8da?fccid=3a3a43367e45f57e&vjs=3",
        "summary": "\nExperience of delivering sports, health or fitness programs.\nUKAG Gymnastics & Trampolining Coaching Level 2 Certificate for Level 1 Coaches and Teachers*.\n",
        "creation_date": "EmployerActive 3 days ago",
        "saved_date": "2023-06-17"
    },
    {
        "name": "Swim Teacher",
        "company": "Everyone Active",
        "location": "Thatcham+4 locations",
        "url": "https://uk.indeed.com/company/Everyone-Active/jobs/Swim-Instructor-68ef54dabd6ce5b2?fccid=0b7134f5982ee145&vjs=3",
        "summary": "\nSwim England Level 2 Swim Teacher Qualification (preferred).\nCome and work with us, you\u2019ll receive a supremely competitive hourly rate, ongoing training and\u2026\n",
        "creation_date": "PostedPosted 13 days ago",
        "saved_date": "2023-06-17"
    },
    {
        "name": "Swimming Instructor",
        "company": "Everyone Active",
        "location": "Bristol",
        "url": "https://uk.indeed.com/company/Everyone-Active/jobs/Swim-Instructor-fc8cdfff92bf9682?fccid=0b7134f5982ee145&vjs=3",
        "summary": "\nCome and work with us, you\u2019ll receive a supremely competitive hourly rate, ongoing training and work in a lively and friendly environment.\n",
        "creation_date": "PostedPosted 30+ days ago",
        "saved_date": "2023-06-17"
    },
    {
        "name": "Cover Supervisor/ Instructor",
        "company": "Now Education",
        "location": "Leicester",
        "url": "https://uk.indeed.com/company/Now-Education/jobs/Cover-Supervisor-e376371e0b87187d?fccid=cd14588072df0a4a&vjs=3",
        "summary": "\nWe are currently recruiting for a high calibre Cover Supervisor/ Instructor to lead across a wide variety of cover lessons throughout the week and support\u2026\n",
        "creation_date": "EmployerActive 3 days ago",
        "saved_date": "2023-06-17"
    },
    {
        "name": "Gymnastics and Trampolining Coaches - Qualified and Unqualified positions",
        "company": "UK Academies of Gymnastics - Totton Gymnastics...",
        "location": "Southampton",
        "url": "https://uk.indeed.com/company/UK-Academies-of-Gymnastics---Totton-Gymnastics-Academy/jobs/Gymnastics-Coach-53ef100eea0397f2?fccid=3a3a43367e45f57e&vjs=3",
        "summary": "\nExperience of delivering sports, health or fitness programs.\nUKAG Gymnastics & Trampolining Coaching Level 2 Certificate for Level 1 Coaches and Teachers*.\n",
        "creation_date": "EmployerActive 3 days ago",
        "saved_date": "2023-06-17"
    },
    {
        "name": "Gymnastics and Trampolining Coaches - Qualified and Unqualified positions",
        "company": "UK Academies of Gymnastics - Wareham Gymnastics...",
        "location": "Worth Matravers",
        "url": "https://uk.indeed.com/company/UK-Academies-of-Gymnastics---Wareham-Gymnastics-Academy/jobs/Gymnastics-Coach-b261c9334fa8fc5b?fccid=e1f279a852e45b89&vjs=3",
        "summary": "\nExperience of delivering sports, health or fitness programs.\nUKAG Gymnastics & Trampolining Coaching Level 2 Certificate for Level 1 Coaches and Teachers*.\n",
        "creation_date": "EmployerActive 3 days ago",
        "saved_date": "2023-06-17"
    },
    {
        "name": "Basketball Coach",
        "company": "Full of Beans Children's Fitness & Sports Coaching",
        "location": "Newcastle upon Tyne",
        "url": "https://uk.indeed.com/company/Full-of-Beans-Fitness-Ltd/jobs/Basketball-Coach-d5853d56a342ccd0?fccid=f61578951376e4a0&vjs=3",
        "summary": "\nWe are looking for a Level 2 qualified and experienced Basketball coach to deliver after school clubs and Community clubs.\n",
        "creation_date": "EmployerActive 6 days ago",
        "saved_date": "2023-06-17"
    },
    {
        "name": "Teacher of PE",
        "company": "Dove House School",
        "location": "Basingstoke",
        "url": "https://uk.indeed.com/company/Dove-House-School/jobs/Physical-Education-Teacher-37d1b4552a0ad39d?fccid=1355be7363412dd4&vjs=3",
        "summary": "\nDove House are seeking to recruit a full time PE teacher, to include tutor responsibility, from September 2023.\nSkilled in either Primary or Secondary teaching.\n",
        "creation_date": "EmployerActive 3 days ago",
        "saved_date": "2023-06-17"
    },
    {
        "name": "Duty Manager (Fitness) - Full Time - Arun Leisure Centre",
        "company": "Freedom Leisure",
        "location": "Bognor Regis PO22",
        "url": "https://uk.indeed.com/rc/clk?jk=d452032b877e9525&fccid=b7fc9a95cd7d047c&vjs=3",
        "summary": "\nLeadership of the fitness team including gym instructors and group exercise instructors.\nThis role would be ideally suited to someone from a leisure centre or\u2026\n",
        "creation_date": "PostedPosted 30+ days ago",
        "saved_date": "2023-06-17"
    },
    {
        "name": "Athletics Coach",
        "company": "Our Parks Ltd",
        "location": "Kingston upon Thames",
        "url": "https://uk.indeed.com/company/Our-Parks/jobs/Athletics-Coach-9a3cc1c0d5aa0e0a?fccid=b55551157b36c3b5&vjs=3",
        "summary": "\nMinimum Level 2 Coaching certificate.\nMinimum Level 2 Coaching Qualification (required).\nThis is a Freelance position with no contract and pay will be monthly.\n",
        "creation_date": "Employer30+ days ago",
        "saved_date": "2023-06-17"
    },
    {
        "name": "Swimming Instructors - Cover Teachers",
        "company": "H2o Swimming Academy",
        "location": "Kettering",
        "url": "https://uk.indeed.com/company/H2o-Swimming-Academy/jobs/Swim-Instructor-915b5acca5225e3a?fccid=b8bb39f65dbab7e7&vjs=3",
        "summary": "\nLevel 2 Swim England/ASA or STA Certificate Qualification or equivalent.\nThe learn to swim classes are children\u2019s group lessons with a maximum of 6 children per\u2026\n",
        "creation_date": "EmployerActive 4 days ago",
        "saved_date": "2023-06-17"
    },
    {
        "name": "Spin Instructor - Casual - Crowborough Leisure Centre",
        "company": "Freedom Leisure",
        "location": "Crowborough",
        "url": "https://uk.indeed.com/rc/clk?jk=c0e47291b118cafc&fccid=b7fc9a95cd7d047c&vjs=3",
        "summary": "\nRewarding role supporting health & fitness in the community.\nNationally recognised group exercise qualification.\n",
        "creation_date": "EmployerActive 9 days ago",
        "saved_date": "2023-06-17"
    },
    {
        "name": "Gymnastics Coach",
        "company": "ClubNorth Gymnastics",
        "location": "London",
        "url": "https://uk.indeed.com/company/ClubNorth-Gymnastics/jobs/Gymnastics-Coach-b376d300b4a88548?fccid=b5656eccb4ed9149&vjs=3",
        "summary": "\nClasses are a maximum of 12 pupils with a ratio of one British Gymnastics instructor for every six pupils.\nA passion for gymnastics and teaching high-quality\u2026\n",
        "creation_date": "EmployerActive 16 days ago",
        "saved_date": "2023-06-17"
    },
    {
        "name": "Gymnastics Instructor",
        "company": "Love Care Recruitment",
        "location": "London W12",
        "url": "https://uk.indeed.com/company/Love-Care-Recruitment/jobs/Gymnastics-Instructor-6c93c7621eed90c6?fccid=7c52c602787bbf7d&vjs=3",
        "summary": "\nAs an instructor you will be hosting a whole range of classes including gymnastics, tumbling and movement.\nStrong basic with the ability to increase pay.\n",
        "creation_date": "EmployerActive 15 days ago",
        "saved_date": "2023-06-17"
    },
    {
        "name": "Gymnastics and Trampolining Coaches - Qualified and Unqualified positions",
        "company": "UK Academies of Gymnastics - Matlock Gymnastics...",
        "location": "Matlock",
        "url": "https://uk.indeed.com/company/UK-Academies-of-Gymnastics---Totton-Gymnastics-Academy/jobs/Gymnastics-Coach-afc86d717e30a5b1?fccid=3a3a43367e45f57e&vjs=3",
        "summary": "\nExperience of delivering sports, health or fitness programs.\nUKAG Gymnastics & Trampolining Coaching Level 2 Certificate for Level 1 Coaches and Teachers*.\n",
        "creation_date": "EmployerActive 3 days ago",
        "saved_date": "2023-06-17"
    },
    {
        "name": "Female Gymnastics Instructor",
        "company": "Bahja Initiative",
        "location": "Accrington BB5",
        "url": "https://uk.indeed.com/company/Afrah-Al-Batul/jobs/Gymnastics-Instructor-0844dc28865a6ca4?fccid=e8ba259ee477c696&vjs=3",
        "summary": "\nExperience as an instructor is desirable.\nPart-time hours: 2 per week.\nProjects have included tackling poverty through a food bank and weekly hot food meals\u2026\n",
        "creation_date": "PostedPosted 30+ days ago",
        "saved_date": "2023-06-17"
    },
    {
        "name": "Swimming Teacher",
        "company": "Everyone Active",
        "location": "Flitwick",
        "url": "https://uk.indeed.com/company/Everyone-Active/jobs/Swim-Instructor-ebf30124bc41e172?fccid=0b7134f5982ee145&vjs=3",
        "summary": "\nParent and Child teachers required.*.\nCome and work with us, you\u2019ll receive a supremely competitive hourly rate, ongoing training and work in a lively and\u2026\n",
        "creation_date": "PostedToday",
        "saved_date": "2023-06-17"
    },
    {
        "name": "Pilates Instructor",
        "company": "Rise Reformer Pilates",
        "location": "Yarm",
        "url": "https://uk.indeed.com/company/Rise-Reformer-Pilates/jobs/Pilates-Instructor-c4b308d6df4a489c?fccid=a1448cfce909417d&vjs=3",
        "summary": "\nA passion for fitness and a commitment to helping clients achieve their goals.\nYou should be experienced in teaching fitness classes and have a passion for\u2026\n",
        "creation_date": "EmployerActive 4 days ago",
        "saved_date": "2023-06-17"
    },
    {
        "name": "Science After School Club Instructor (FT)",
        "company": "Bright Sparks Science",
        "location": "Abingdon",
        "url": "https://uk.indeed.com/rc/clk?jk=7bc163270f8c8e35&fccid=06f20797bca5b2c2&vjs=3",
        "summary": "\nThe employers\u2019 contributions are set at 3% of staff\u2019s earnings and workers will contribute 5% of their earnings.\nUndertaking appropriate and relevant training.\n",
        "creation_date": "PostedPosted 11 days ago",
        "saved_date": "2023-06-17"
    },
    {
        "name": "Gymnastics and Trampolining Coaches - Qualified and Unqualified positions",
        "company": "UK Academies of Gymnastics - Basingstoke...",
        "location": "Basingstoke RG22",
        "url": "https://uk.indeed.com/company/UK-Academies-of-Gymnastics---Totton-Gymnastics-Academy/jobs/Gymnastics-Coach-4002cc3ae70af46f?fccid=3a3a43367e45f57e&vjs=3",
        "summary": "\nExperience of delivering sports, health or fitness programs.\nUKAG Gymnastics & Trampolining Coaching Level 2 Certificate for Level 1 Coaches and Teachers*.\n",
        "creation_date": "EmployerActive 3 days ago",
        "saved_date": "2023-06-17"
    },
    {
        "name": "Duty Manager/Team Leader",
        "company": "Energie Fitness",
        "location": "Erith",
        "url": "https://uk.indeed.com/company/Fit4Less/jobs/Duty-Manager-bc95aecd81b67e4c?fccid=a74b26f851a05607&vjs=3",
        "summary": "\nOffering free gym trials to local businesses and members of the public.\nBe responsible for the smooth running of our club.\n",
        "creation_date": "PostedPosted 1 day ago",
        "saved_date": "2023-06-17"
    },
    {
        "name": "Gymnastics Instructor",
        "company": "Places Leisure - The Triangle",
        "location": "Burgess Hill",
        "url": "https://uk.indeed.com/company/Places-Leisure/jobs/Gymnastics-Instructor-cf4b8eab60d0f5d6?fccid=03758924a2ae0f26&vjs=3",
        "summary": "\nYou will work with customers in groups and sometimes on a one-to-one basis to motivate and instruct them during their lessons.\nJob Type: Zero hours contract.\n",
        "creation_date": "PostedPosted 30+ days ago",
        "saved_date": "2023-06-17"
    },
    {
        "name": "Primary School Sports Coach",
        "company": "Changing Lives Community Services",
        "location": "Harlow",
        "url": "https://uk.indeed.com/company/Changing-Lives-Community-Services/jobs/Sports-Coach-e5f371a5e7eb2b67?fccid=e0eb483637b5798f&vjs=3",
        "summary": "\nDelivering a variety of sports and physical activity sessions to groups of up to 30 children;\nEncouraging children to engage and have fun during sessions;\n",
        "creation_date": "EmployerActive 4 days ago",
        "saved_date": "2023-06-17"
    },
    {
        "name": "Learning Support Assistant (SEMH)",
        "company": "Masterclass Education",
        "location": "Horsham",
        "url": "https://uk.indeed.com/company/MasterClass/jobs/Support-Associate-1d5756e0e607abfd?fccid=665a184a85b4c182&vjs=3",
        "summary": "\nMasterclass Education are working closely with a specialist school on the outskirts of Horsham who are looking for Learning Support Assistants to join their\u2026\n",
        "creation_date": "PostedPosted 30+ days ago",
        "saved_date": "2023-06-17"
    },
    {
        "name": "Teaching Assistant (SEN Support)",
        "company": "Masterclass Education",
        "location": "Hove",
        "url": "https://uk.indeed.com/company/MasterClass/jobs/Teaching-Assistant-44999c302661f4bf?fccid=665a184a85b4c182&vjs=3",
        "summary": "\n\u00a370 - \u00a380 day rate.\nHove, East Sussex | Monday - Friday | 8:30am - 3:00pm | Term time only.\nDo you have a clean, full UK driving license and access to your\u2026\n",
        "creation_date": "PostedPosted 30+ days ago",
        "saved_date": "2023-06-17"
    },
    {
        "name": "Learning Support Assistant (SEN)",
        "company": "Masterclass Education",
        "location": "Crawley",
        "url": "https://uk.indeed.com/company/MasterClass/jobs/Support-Associate-5126b374842035ca?fccid=665a184a85b4c182&vjs=3",
        "summary": "\n\u00a370 - \u00a380 day rate.\nCrawley, West Sussex | Monday - Friday | 8:30am - 3:00pm | Term time only.\nMasterclass Education are working closely with a specialist\u2026\n",
        "creation_date": "PostedPosted 30+ days ago",
        "saved_date": "2023-06-17"
    }
]