[
    {
        "name": "Landscape Architect",
        "company": "Norfolk County Council",
        "location": "Remote in Norwich NR1",
        "url": "https://uk.indeed.com/rc/clk?jk=eae705dcf893d6c5&fccid=229a6d561c5eb022&vjs=3",
        "summary": "\nThe role requires knowledge and experience in the preparation of detailed landscape designs and masterplans, whilst ensuring that all work undertaken can\u2026\n",
        "creation_date": "PostedPosted 10 days ago",
        "saved_date": "2023-06-17"
    },
    {
        "name": "Graduate Landscape Architect",
        "company": "Sweco UK",
        "location": "Hybrid remote in Manchester M1+2 locations",
        "url": "https://uk.indeed.com/rc/clk?jk=d162c2b2d98dc32f&fccid=51ae940969add7a1&vjs=3",
        "summary": "\nYou will be working with multi-disciplinary design teams taking projects through the planning process from site feasibility studies and landscape impact\u2026\n",
        "creation_date": "PostedPosted 11 days ago",
        "saved_date": "2023-06-17"
    },
    {
        "name": "Graduate Landscape Architect - People & Places Solutions",
        "company": "Jacobs",
        "location": "Hybrid remote in Birmingham",
        "url": "https://uk.indeed.com/rc/clk?jk=e743c3e3b19a4f08&fccid=de56d7554bea5214&vjs=3",
        "summary": "\nOur Graduate Development Programme is a structured 2-year scheme, aiming to progress Graduates into global project leaders and problem solvers.\n",
        "creation_date": "PostedPosted 30+ days ago",
        "saved_date": "2023-06-17"
    },
    {
        "name": "Senior Landscape Architect",
        "company": "Linear Recruitment",
        "location": "Hybrid remote in London+1 location",
        "url": "https://uk.indeed.com/rc/clk?jk=d24022e33fe801ec&fccid=073a77ac2cdeb378&vjs=3",
        "summary": "We are looking to speak to Senior Landscape Architects. Linear recruitment had an opportunity with a well-known top 20 AJ100 practice based in London; our\u2026",
        "creation_date": "PostedPosted 16 days ago",
        "saved_date": "2023-06-17"
    },
    {
        "name": "Assistant Landscape Architect - Bristol",
        "company": "Atkins",
        "location": "Bristol+1 location",
        "url": "https://uk.indeed.com/rc/clk?jk=af605020c3bac09e&fccid=d67cac272a1a8c54&vjs=3",
        "summary": "\nYou will need a Degree, Post Graduate Diploma or Masters qualification in landscape architecture ideally with a minimum 2 years post-graduate experience and be\u2026\n",
        "creation_date": "PostedPosted 30+ days ago",
        "saved_date": "2023-06-17"
    },
    {
        "name": "Graduate Landscape Architect",
        "company": "Green Path Recruitment",
        "location": "London+1 location",
        "url": "https://uk.indeed.com/rc/clk?jk=c486e46df07ed68a&fccid=c85409ba7f33052d&vjs=3",
        "summary": "\nYou will have a good understanding of issues affecting landscape architecture at various stages in the design process and a broad based understanding of detail\u2026\n",
        "creation_date": "PostedPosted 30+ days ago",
        "saved_date": "2023-06-17"
    },
    {
        "name": "Landscape Designer",
        "company": "BIG (Bjarke Ingels Group)",
        "location": "London",
        "url": "https://uk.indeed.com/rc/clk?jk=8d1a9e1d79d83ccf&fccid=a95065f1acf63fd2&vjs=3",
        "summary": "\nA minimum of 3 years professional experience as a landscape designer/architect on large-scale projects.\nExperience with landscape exercises on masterplans is a\u2026\n",
        "creation_date": "PostedPosted 30+ days ago",
        "saved_date": "2023-06-17"
    },
    {
        "name": "Landscape Architect or experienced Landscape Assistant - Bristol",
        "company": "AHR",
        "location": "Bristol",
        "url": "https://uk.indeed.com/rc/clk?jk=065a0050dcffe9c4&fccid=8c96e89e1f0b0f23&vjs=3",
        "summary": "\nWe have an exciting opportunity for a landscape architect or an experienced landscape assistant with a minimum of 2 years professional experience to join our\u2026\n",
        "creation_date": "PostedPosted 30+ days ago",
        "saved_date": "2023-06-17"
    },
    {
        "name": "Principal Landscape Architect - Edinburgh",
        "company": "Marston Holding Limited",
        "location": "Edinburgh",
        "url": "https://uk.indeed.com/rc/clk?jk=fab9075891909ffe&fccid=778522e4b7297b3a&vjs=3",
        "summary": "\nDetailed technical knowledge of public realm design, landscape architecture and/or master planning.\nWe offer a range of services focused on providing our\u2026\n",
        "creation_date": "PostedPosted 30+ days ago",
        "saved_date": "2023-06-17"
    },
    {
        "name": "Landscape Architect",
        "company": "Perth & Kinross Council",
        "location": "Perth PH1",
        "url": "https://uk.indeed.com/rc/clk?jk=9db9f503ad7d7e93&fccid=34b0ed66ddee9736&vjs=3",
        "summary": "\nYou will have to respond in a timely manner to MSP, MP and Councillor queries and public service requests and complaints and provide specialist landscape advice\u2026\n",
        "creation_date": "PostedPosted 23 days ago",
        "saved_date": "2023-06-17"
    },
    {
        "name": "Associate Landscape Architect",
        "company": "Morgan Hunt",
        "location": "Hybrid remote in Scotland",
        "url": "https://uk.indeed.com/rc/clk?jk=68ff324bdb0560d1&fccid=6ff710164a732464&vjs=3",
        "summary": "\nEnvironmental improvement and landscape strategies.\nExperience of landscape planning / LVIA for other infrastructure projects (e.g. residential, commercial,\u2026\n",
        "creation_date": "PostedPosted 30+ days ago",
        "saved_date": "2023-06-17"
    },
    {
        "name": "Senior Landscape Architect",
        "company": "SLR Consulting",
        "location": "Edinburgh+1 location",
        "url": "https://uk.indeed.com/rc/clk?jk=ebbe07b4c7324a4d&fccid=549bbce028d52285&vjs=3",
        "summary": "\nWe are looking for an experienced Senior Landscape Architect or Landscape Architect to join OPEN's studio in Edinburgh and to work on a range of amazing\u2026\n",
        "creation_date": "PostedPosted 30+ days ago",
        "saved_date": "2023-06-17"
    },
    {
        "name": "Senior Landscape Architect - Slough",
        "company": "Marston Holding Limited",
        "location": "Slough",
        "url": "https://uk.indeed.com/rc/clk?jk=b78382a89957b505&fccid=778522e4b7297b3a&vjs=3",
        "summary": "\nUnderstanding of urban design / landscape architecture principles.\nTo assist in the delivery of urban design and landscape architecture projects in the public\u2026\n",
        "creation_date": "PostedPosted 30+ days ago",
        "saved_date": "2023-06-17"
    },
    {
        "name": "Landscape Architect (chartered)",
        "company": "Allies and Morrison",
        "location": "London",
        "url": "https://uk.indeed.com/rc/clk?jk=d7f33874ec0b6b19&fccid=c69046c4f79d6cf0&vjs=3",
        "summary": "\nAn established practical project use of 3D modelling experience, Rhino and Revit a plus.\n",
        "creation_date": "PostedPosted 30+ days ago",
        "saved_date": "2023-06-17"
    },
    {
        "name": "Landscape or Senior Landscape Architects (London, Edinburgh, Bristol or Manchester)",
        "company": "HTA",
        "location": "Hybrid remote in London",
        "url": "https://uk.indeed.com/rc/clk?jk=589c100b9ea63bdb&fccid=f2170e3af673d513&vjs=3",
        "summary": "\nWe are interested in hearing from Chartered (or near Chartered) Landscape and Senior Landscape Architects with extensive project delivery, studio and site\u2026\n",
        "creation_date": "PostedPosted 30+ days ago",
        "saved_date": "2023-06-17"
    },
    {
        "name": "Landscape Architect / Project Landscape Architect",
        "company": "planit-ie",
        "location": "Hybrid remote in Standish",
        "url": "https://uk.indeed.com/rc/clk?jk=60140e84ccf46f6a&fccid=4b8c45b43e8c8bd3&vjs=3",
        "summary": "\nFull-time Landscape Architect and Project Landscape Architect sought to join Planit-IE\u2019s Standish studio \u2014 The Gatehouse and 5th Studio in Gloucestershire.\n",
        "creation_date": "PostedPosted 30+ days ago",
        "saved_date": "2023-06-17"
    },
    {
        "name": "Landscape Architect",
        "company": "Anderselite",
        "location": "Gloucestershire+1 location",
        "url": "https://uk.indeed.com/rc/clk?jk=e3daf9ad43197df8&fccid=54d1dee5bece0679&vjs=3",
        "summary": "\nAssist the production of illustrative design information including landscape strategy plans and landscape masterplans, to support a range of developments\u2026\n",
        "creation_date": "PostedPosted 30+ days ago",
        "saved_date": "2023-06-17"
    },
    {
        "name": "Project / Senior Landscape Architect",
        "company": "planit-ie",
        "location": "Hybrid remote in Leeds",
        "url": "https://uk.indeed.com/rc/clk?jk=ed51c5d8c76d8f87&fccid=4b8c45b43e8c8bd3&vjs=3",
        "summary": "\nRecently completed projects include the redefined setting to the Corn Exchange, Sovereign Bridge Footbridge and Meadow Lane Green Space.\n",
        "creation_date": "PostedPosted 30+ days ago",
        "saved_date": "2023-06-17"
    },
    {
        "name": "Landscape Architect (all levels considered)",
        "company": "Anderselite",
        "location": "Bath",
        "url": "https://uk.indeed.com/rc/clk?jk=c537fdb64f5c370d&fccid=54d1dee5bece0679&vjs=3",
        "summary": "\nHave experience and/or an interest in undertaking landscape and visual assessment surveys and reports.\nThe post would be a permanent, full time position for 37\u2026\n",
        "creation_date": "PostedPosted 30+ days ago",
        "saved_date": "2023-06-17"
    },
    {
        "name": "Principal Landscape Architect",
        "company": "Green Path Recruitment",
        "location": "London",
        "url": "https://uk.indeed.com/rc/clk?jk=0411df330f108fa1&fccid=c85409ba7f33052d&vjs=3",
        "summary": "\nIdeally you will be a creative designer with strong communication skills and a proven track record in the successful delivery of high quality landscape and\u2026\n",
        "creation_date": "PostedPosted 30+ days ago",
        "saved_date": "2023-06-17"
    },
    {
        "name": "Landscape Architect",
        "company": "Amey plc",
        "location": "Manchester+1 location",
        "url": "https://uk.indeed.com/rc/clk?jk=2a084b56bf9234d2&fccid=b1d187bd2a99600f&vjs=3",
        "summary": "\nInterest in all areas of landscape design and assessment.\nCollaborating with multidisciplinary teams to integrate landscape design into overall project plans.\n",
        "creation_date": "PostedPosted 30+ days ago",
        "saved_date": "2023-06-17"
    },
    {
        "name": "Landscape/Senior Landscape Architect 50/50 Home working",
        "company": "Green Path Recruitment",
        "location": "Remote in London",
        "url": "https://uk.indeed.com/rc/clk?jk=9133e41e19932ba5&fccid=c85409ba7f33052d&vjs=3",
        "summary": "\nI am looking to talk with Project Landscape Architects will a rounded experience and capabilities working front-end in design as well as good levels of\u2026\n",
        "creation_date": "PostedPosted 30+ days ago",
        "saved_date": "2023-06-17"
    },
    {
        "name": "Contract Landscape Architect",
        "company": "Green Path Recruitment",
        "location": "London",
        "url": "https://uk.indeed.com/rc/clk?jk=971779bef37431b9&fccid=c85409ba7f33052d&vjs=3",
        "summary": "\nThe ideal candidate will have some international project experience obtained working for a UK based consultancy.\n",
        "creation_date": "PostedPosted 30+ days ago",
        "saved_date": "2023-06-17"
    },
    {
        "name": "Assistant Landscape Architect",
        "company": "Green Path Recruitment",
        "location": "London+1 location",
        "url": "https://uk.indeed.com/rc/clk?jk=df453c7c6607398d&fccid=c85409ba7f33052d&vjs=3",
        "summary": "\nOffering specialist architectural, town planning and landscape design advice, the practice\u2019s strong communication skills, honest objective opinions and\u2026\n",
        "creation_date": "PostedPosted 30+ days ago",
        "saved_date": "2023-06-17"
    },
    {
        "name": "Landscape Architect - Chartered",
        "company": "Gensler",
        "location": "London",
        "url": "https://uk.indeed.com/rc/clk?jk=fc6a27a0ec377315&fccid=7108e42f22171d5c&vjs=3",
        "summary": "\nApplicants should be either chartered already or be eligible for the landscape institute Pathway to Chartership with the desire to gain professional licensure.\n",
        "creation_date": "PostedPosted 30+ days ago",
        "saved_date": "2023-06-17"
    },
    {
        "name": "Landscape Architect",
        "company": "Pertemps Network Group",
        "location": "Cheltenham+1 location",
        "url": "https://uk.indeed.com/rc/clk?jk=3a135d5bed79ded7&fccid=1976b8742794eede&vjs=3",
        "summary": "\nThey encourage and develop positive designs that provide excellent biodiversity benefits and innovative solutions across a range of projects from residential to\u2026\n",
        "creation_date": "PostedPosted 15 days ago",
        "saved_date": "2023-06-17"
    },
    {
        "name": "Consultant Landscape Architect",
        "company": "Anderselite",
        "location": "London",
        "url": "https://uk.indeed.com/rc/clk?jk=edc3d0186d49791c&fccid=54d1dee5bece0679&vjs=3",
        "summary": "\nThorough knowledge and understanding of the UK legal and planning system with respect to landscape architecture.\n",
        "creation_date": "PostedPosted 30+ days ago",
        "saved_date": "2023-06-17"
    },
    {
        "name": "Associate Landscape Architect",
        "company": "Green Path Recruitment",
        "location": "London",
        "url": "https://uk.indeed.com/rc/clk?jk=661bc0f0b826f2f6&fccid=c85409ba7f33052d&vjs=3",
        "summary": "\nOur client is looking for an Associate Landscape Architect and a senior with 5-10 years\u2019 experience for their London studio.\n",
        "creation_date": "PostedPosted 30+ days ago",
        "saved_date": "2023-06-17"
    },
    {
        "name": "Chartered Landscape Architect",
        "company": "Norse Group",
        "location": "London SW6",
        "url": "https://uk.indeed.com/rc/clk?jk=e10ccba2692685ed&fccid=104501f852d7f1f3&vjs=3",
        "summary": "\nAdvising clients and project teams on relevant landscape matters for planning, landscape management, and biodiversity.\n27 days annual leave plus bank holidays.\n",
        "creation_date": "PostedPosted 30+ days ago",
        "saved_date": "2023-06-17"
    },
    {
        "name": "Chartered Senior Landscape Architect",
        "company": "Atkins",
        "location": "Edinburgh",
        "url": "https://uk.indeed.com/rc/clk?jk=a24a97549b79fb97&fccid=d67cac272a1a8c54&vjs=3",
        "summary": "\nProvision of landscape advice to clients.\nLead design input to a range of projects, including infrastructure, public realm, urban regeneration and design\u2026\n",
        "creation_date": "PostedPosted 30+ days ago",
        "saved_date": "2023-06-17"
    },
    {
        "name": "Landscape architect",
        "company": "Linear Recruitment",
        "location": "Hybrid remote in York",
        "url": "https://uk.indeed.com/rc/clk?jk=29ed17c98e74028f&fccid=073a77ac2cdeb378&vjs=3",
        "summary": "\nAnd strategies, planning submissions, including landscape and visual assessment, through to detailed landscape design.\n\u00a332-45k salary depending on experience.\n",
        "creation_date": "PostedPosted 30+ days ago",
        "saved_date": "2023-06-17"
    },
    {
        "name": "Associate Landscape Architect",
        "company": "Hunter Dunning",
        "location": "North London+1 location",
        "url": "https://uk.indeed.com/rc/clk?jk=f8ce815d988d3cac&fccid=4c282c99b24de24a&vjs=3",
        "summary": "\nProven knowledge of design and detailing on landscape projects.\nExperience in landscape architecture at a senior level is essential.\n3 days per week contract.\n",
        "creation_date": "PostedPosted 30+ days ago",
        "saved_date": "2023-06-17"
    },
    {
        "name": "Landscape Architect",
        "company": "Green Path Recruitment",
        "location": "London+1 location",
        "url": "https://uk.indeed.com/rc/clk?jk=43f3bd103aa4de11&fccid=c85409ba7f33052d&vjs=3",
        "summary": "\nWork on a range of tasks including landscape design, landscape planning and Environmental Impact Assessment.\nAssisting in delivering projects to a high standard\u2026\n",
        "creation_date": "PostedPosted 30+ days ago",
        "saved_date": "2023-06-17"
    },
    {
        "name": "Senior Landscape Architect - Bristol or Cardiff",
        "company": "Atkins",
        "location": "Bristol",
        "url": "https://uk.indeed.com/rc/clk?jk=fa94126768d2a349&fccid=d67cac272a1a8c54&vjs=3",
        "summary": "\nProvision of landscape advice to external and internal clients.\nResource allocation in liaison with the landscape senior leadership team.\n",
        "creation_date": "PostedPosted 30+ days ago",
        "saved_date": "2023-06-17"
    },
    {
        "name": "Landscape Architect",
        "company": "Bennett & Game Recruitment",
        "location": "Hybrid remote in Cheltenham+5 locations",
        "url": "https://uk.indeed.com/rc/clk?jk=9bf31c931ce5da8a&fccid=779e6996af0c8263&vjs=3",
        "summary": "\nProvide landscape design and landscape management services.\nUndertake landscape design work as instructed by clients and senior members of staff.\n",
        "creation_date": "PostedPosted 30+ days ago",
        "saved_date": "2023-06-17"
    },
    {
        "name": "Senior Chartered Landscape Architect",
        "company": "BDP UK",
        "location": "Hybrid remote in London",
        "url": "https://uk.indeed.com/rc/clk?jk=ea7e9f4ef4a4f13e&fccid=0b6f063a87bd0bbf&vjs=3",
        "summary": "\nYou will have a degree in Landscape Architecture.\nYou will have an attractive hand drawing style or equivalent skill in quickly visualising designs for clients\u2026\n",
        "creation_date": "PostedPosted 30+ days ago",
        "saved_date": "2023-06-17"
    },
    {
        "name": "Chartered Landscape Architect",
        "company": "BDP UK",
        "location": "London",
        "url": "https://uk.indeed.com/rc/clk?jk=d44a2579c4608b66&fccid=0b6f063a87bd0bbf&vjs=3",
        "summary": "\nYou will have a degree in Landscape Architecture.\nYou will have an attractive hand drawing style or equivalent skill in quickly visualising designs for clients\u2026\n",
        "creation_date": "PostedPosted 30+ days ago",
        "saved_date": "2023-06-17"
    },
    {
        "name": "Landscape Architect - Associate Director",
        "company": "Taylor Herrick Recruitment",
        "location": "Warwickshire",
        "url": "https://uk.indeed.com/rc/clk?jk=8c39a0107710381e&fccid=98c01b4ef3b0529d&vjs=3",
        "summary": "\nYou will work directly with clients, architects, urban designers, and environmental consultants to provide professional and reliable judgements and\u2026\n",
        "creation_date": "PostedPosted 30+ days ago",
        "saved_date": "2023-06-17"
    },
    {
        "name": "Senior Landscape Designer",
        "company": "SLR Consulting",
        "location": "Bristol",
        "url": "https://uk.indeed.com/rc/clk?jk=f0bfe8476a27f51d&fccid=549bbce028d52285&vjs=3",
        "summary": "\nWith high quality consultancy experience, you will work alongside and have the support of some of the UK\u2019s leading landscape experts.\n",
        "creation_date": "PostedPosted 30+ days ago",
        "saved_date": "2023-06-17"
    },
    {
        "name": "Senior Landscape Architect",
        "company": "Amey plc",
        "location": "Belfast+1 location",
        "url": "https://uk.indeed.com/rc/clk?jk=5f1118252d042ad4&fccid=b1d187bd2a99600f&vjs=3",
        "summary": "\nAdvise on landscape aspects of projects including but not limited to EIAs, LVIAs, VIAs.\nKeep up to date with industry best practice and where, appropriate,\u2026\n",
        "creation_date": "PostedPosted 30+ days ago",
        "saved_date": "2023-06-17"
    },
    {
        "name": "Senior Landscape Architect",
        "company": "Mattinson Partnership",
        "location": "London",
        "url": "https://uk.indeed.com/rc/clk?jk=6ae5cfd1b2133a9b&fccid=976b1232c1ab6bfd&vjs=3",
        "summary": "\nMinimum of 8 years of professional experience in landscape architecture, with a focus on project design and delivery.\n",
        "creation_date": "PostedPosted 11 days ago",
        "saved_date": "2023-06-17"
    },
    {
        "name": "Project Landscape Architect",
        "company": "Green Path Recruitment",
        "location": "London",
        "url": "https://uk.indeed.com/rc/clk?jk=1dc27db70d213184&fccid=c85409ba7f33052d&vjs=3",
        "summary": "We are currently working with a highly acclaimed and award winning Landscape and Urban Design practice, who work across the Middle East and Asia in delivering\u2026",
        "creation_date": "PostedPosted 30+ days ago",
        "saved_date": "2023-06-17"
    },
    {
        "name": "Senior Landscape Architect",
        "company": "Eden Brown",
        "location": "West Midlands+1 location",
        "url": "https://uk.indeed.com/rc/clk?jk=896acf1918049b5e&fccid=76740e7c3237171c&vjs=3",
        "summary": "\nYou will have a creative flair and enjoy exploring innovative landscape techniques as well as the ability to deliver LVIA's and the related workstreams such as\u2026\n",
        "creation_date": "PostedPosted 30+ days ago",
        "saved_date": "2023-06-17"
    },
    {
        "name": "Experienced Landscape Planner (full or part time)",
        "company": "The Landmark Practice",
        "location": "Bristol BS41",
        "url": "https://uk.indeed.com/rc/clk?jk=88f584720cfdcbf0&fccid=d1c83881dc37b1cc&vjs=3",
        "summary": "\nExperience of delivering landscape work (LVIA, TVIA and EIA technical reports landscape strategies and masterplans).\nExcellent time and task management skills.\n",
        "creation_date": "PostedPosted 30+ days ago",
        "saved_date": "2023-06-17"
    },
    {
        "name": "Landscape Architect",
        "company": "Hunter Dunning",
        "location": "Hybrid remote in Brighton+4 locations",
        "url": "https://uk.indeed.com/rc/clk?jk=8472291a5b40b505&fccid=4c282c99b24de24a&vjs=3",
        "summary": "\nTo work towards presenting landscape projects both verbally and graphically to potential clients from private, public sectors.\n",
        "creation_date": "PostedPosted 30+ days ago",
        "saved_date": "2023-06-17"
    },
    {
        "name": "Landscape Architect",
        "company": "Conrad Consulting",
        "location": "Bristol",
        "url": "https://uk.indeed.com/rc/clk?jk=824cc0133ecb75dc&fccid=d1b767ce1de12565&vjs=3",
        "summary": "\nIdeally, we would like to speak with Chartered Landscape Architects with a demonstrable track record in design and assessment - however, we would also like to\u2026\n",
        "creation_date": "PostedPosted 30+ days ago",
        "saved_date": "2023-06-17"
    },
    {
        "name": "Senior Landscape Architect",
        "company": "Green Path Recruitment",
        "location": "South West+1 location",
        "url": "https://uk.indeed.com/rc/clk?jk=93eda74bba920b48&fccid=c85409ba7f33052d&vjs=3",
        "summary": "\nProven experience of undertaking LVIAs and appraisals, landscape character assessments and landscape evidence bases in support of site allocations and planning\u2026\n",
        "creation_date": "PostedPosted 30+ days ago",
        "saved_date": "2023-06-17"
    },
    {
        "name": "Chartered Landscape Architect",
        "company": "Anderselite",
        "location": "Glasgow",
        "url": "https://uk.indeed.com/rc/clk?jk=873f497ebf668b8b&fccid=54d1dee5bece0679&vjs=3",
        "summary": "\nCollaborate with project teams to develop innovative landscape design solutions.\nIn-depth knowledge of landscape design principles and a keen interest in\u2026\n",
        "creation_date": "PostedPosted 24 days ago",
        "saved_date": "2023-06-17"
    },
    {
        "name": "Chartered Landscape Architect",
        "company": "Green Path Recruitment",
        "location": "London+1 location",
        "url": "https://uk.indeed.com/rc/clk?jk=3303a7e959a1f7c8&fccid=c85409ba7f33052d&vjs=3",
        "summary": "\nApplicants must have a degree in Landscape Architecture and the following;\nExceptional design flair and graphic ability.\n",
        "creation_date": "PostedPosted 30+ days ago",
        "saved_date": "2023-06-17"
    },
    {
        "name": "Landscape Contracts Manager",
        "company": "MorePeople",
        "location": "Berkshire",
        "url": "https://uk.indeed.com/rc/clk?jk=e224455fe878b32d&fccid=bbc3fafcd2c666c4&vjs=3",
        "summary": "\nConsulting with those clients, site managers, quantity surveyors and architects will form a bit part of a typical week, so relationship-building and problem\u2026\n",
        "creation_date": "PostedPosted 3 days ago",
        "saved_date": "2023-06-17"
    },
    {
        "name": "Senior Landscape Architect - Exeter",
        "company": "Atkins",
        "location": "Exeter",
        "url": "https://uk.indeed.com/rc/clk?jk=d873bcd17743f093&fccid=d67cac272a1a8c54&vjs=3",
        "summary": "\nProvision of landscape advice to external and internal clients.\nResource allocation in liaison with the landscape senior leadership team.\n",
        "creation_date": "PostedPosted 30+ days ago",
        "saved_date": "2023-06-17"
    },
    {
        "name": "Principal Landscape Architect",
        "company": "Bennett & Game Recruitment",
        "location": "Sheffield",
        "url": "https://uk.indeed.com/rc/clk?jk=47aa17210f9be0bb&fccid=779e6996af0c8263&vjs=3",
        "summary": "\nThe successful Principal Landscape Architect will be involved in all aspects of projects both small and large scale, working alongside and assisting other\u2026\n",
        "creation_date": "PostedPosted 30+ days ago",
        "saved_date": "2023-06-17"
    },
    {
        "name": "Senior Landscape Manager",
        "company": "RSK Group",
        "location": "South East",
        "url": "https://uk.indeed.com/rc/clk?jk=15e4e2192716b9fb&fccid=5a98a9c39839f103&vjs=3",
        "summary": "\nLeading on monitoring landscape aftercare projects.\nProduction and implementation of landscape management instructions.\nUndertake the role of Contracts Manager.\n",
        "creation_date": "PostedPosted 30+ days ago",
        "saved_date": "2023-06-17"
    },
    {
        "name": "Senior Landscape Designer & Master Planning Consultant",
        "company": "GHD",
        "location": "Newcastle upon Tyne",
        "url": "https://uk.indeed.com/rc/clk?jk=7d8802e3ae7b11c0&fccid=25b9aa55f7b71e5c&vjs=3",
        "summary": "\nExperience of working with landscape design software such as AutoCAD, Adobe Suite, Keyscape, Artisan is essential.\nA passion for design and innovation.\n",
        "creation_date": "PostedPosted 30+ days ago",
        "saved_date": "2023-06-17"
    },
    {
        "name": "Graduate/Year Out Landscape Architect",
        "company": "FPCR",
        "location": "Exeter EX3",
        "url": "https://uk.indeed.com/rc/clk?jk=034f43327df7cadd&fccid=cca9edb7bdabf197&vjs=3",
        "summary": "\nYou would work alongside architects, ecologists, arboriculturists and graphic designers within the practice.\nA relevant graduate/ postgraduate qualification in\u2026\n",
        "creation_date": "PostedToday",
        "saved_date": "2023-06-17"
    },
    {
        "name": "Landscape architecture Internship",
        "company": "Hanson UK",
        "location": "Bath",
        "url": "https://uk.indeed.com/company/Hanson/jobs/Architectural-Intern-af1454e88a24e862?fccid=85fd571acb57ba6c&vjs=3",
        "summary": "\nInternship for Hanson UK - Chipping Sodbury - Whetherby - LANDSCAPE ARCHITECTURE, LANDCAPE MANAGEMENT OR ENVIRONMENTAL SCIENCE Degree required - On track for 2\u2026\n",
        "creation_date": "EmployerActive 25 days ago",
        "saved_date": "2023-06-17"
    },
    {
        "name": "Associate Landscape Architect",
        "company": "Pegasus Group",
        "location": "Hybrid remote in Leeds LS25",
        "url": "https://uk.indeed.com/company/Pegasus-Group/jobs/Landscape-Architect-5b134c5784e39189?fccid=cc2744d84b921175&vjs=3",
        "summary": "\nProven understanding and experience in LVIA\u2019s, feasibility studies, landscape planning and design, supporting landscape statements and mitigation strategies;\n",
        "creation_date": "EmployerActive 3 days ago",
        "saved_date": "2023-06-17"
    },
    {
        "name": "Landscape Architect",
        "company": "Gillespies",
        "location": "Hybrid remote in Oxford OX1",
        "url": "https://uk.indeed.com/rc/clk?jk=f79f55eec80d2fc5&fccid=2432fb25a19a4a82&vjs=3",
        "summary": "\nPossess a minimum of 2 years of professional experience in delivering UK and international landscape projects.\nExcellent organisation and presentation skills.\n",
        "creation_date": "PostedPosted 30+ days ago",
        "saved_date": "2023-06-17"
    },
    {
        "name": "Landscape Architect (Permanent)",
        "company": "Redbay Design Ltd",
        "location": "Hybrid remote in Torquay TQ2",
        "url": "https://uk.indeed.com/company/Redbay-Design/jobs/Landscape-Architect-18583ffc891fef64?fccid=8c6fafabbb896629&vjs=3",
        "summary": "\nWe are looking for a landscape professional with a minimum of 3 years post qualification experience.\nYou will have successfully completed an undergraduate\u2026\n",
        "creation_date": "EmployerActive 5 days ago",
        "saved_date": "2023-06-17"
    },
    {
        "name": "Graduate Landscape Architect (Permanent)",
        "company": "Redbay Design Ltd",
        "location": "Torquay TQ2",
        "url": "https://uk.indeed.com/company/Redbay-Design/jobs/Landscape-Architect-61456ac9cc387e97?fccid=8c6fafabbb896629&vjs=3",
        "summary": "\nWith services ranging from landscape appraisal through master-planning to detail design and land management.\nCompetitive salary with flexible start/finish time.\n",
        "creation_date": "EmployerActive 26 days ago",
        "saved_date": "2023-06-17"
    },
    {
        "name": "Landscape Architect",
        "company": "FPCR",
        "location": "Sheffield S3+1 location",
        "url": "https://uk.indeed.com/rc/clk?jk=0884ad1a268c27aa&fccid=cca9edb7bdabf197&vjs=3",
        "summary": "\nWe are seeking talented individuals to help support the continued growth of the practice, working on a wide variety of projects involving masterplanning, green\u2026\n",
        "creation_date": "PostedPosted 2 days ago",
        "saved_date": "2023-06-17"
    },
    {
        "name": "Year-Out Landscape Architect",
        "company": "FPCR",
        "location": "Derby DE74",
        "url": "https://uk.indeed.com/rc/clk?jk=26068379c4f8f90e&fccid=cca9edb7bdabf197&vjs=3",
        "summary": "\nWe are seeking a talented individual to help support the continued growth of the practice, working on a wide variety of projects involving masterplanning, green\u2026\n",
        "creation_date": "EmployerActive 4 days ago",
        "saved_date": "2023-06-17"
    },
    {
        "name": "Year Out Landscape Architect/ Architectural Assistant",
        "company": "FPCR",
        "location": "Derby DE74",
        "url": "https://uk.indeed.com/rc/clk?jk=db493ef39085e53a&fccid=cca9edb7bdabf197&vjs=3",
        "summary": "\nWe are seeking a talented individual to help support the continued growth of the practice, working on a wide variety of projects involving masterplanning,\u2026\n",
        "creation_date": "EmployerActive 4 days ago",
        "saved_date": "2023-06-17"
    },
    {
        "name": "Landscape Architect - ASAP Start",
        "company": "Hunter Mason",
        "location": "Milton Keynes",
        "url": "https://uk.indeed.com/company/Hunter-Mason/jobs/Landscape-Architect-89e08f75f9edad31?fccid=942131a66b68f6c5&vjs=3",
        "summary": "\n3 days working in the office - 2 days hybrid.\nYou MUST have 2-5 years experience in a similar role.\nResponsible for small to large-scale projects, assessment of\u2026\n",
        "creation_date": "EmployerActive 15 days ago",
        "saved_date": "2023-06-17"
    },
    {
        "name": "Landscape Architecture jobs in London",
        "company": "Lead Careers",
        "location": "London",
        "url": "https://uk.indeed.com/rc/clk?jk=c1ed9bc2d5196ca8&fccid=ce9f793e950d986a&vjs=3",
        "summary": "Role \u2013 Landscape Architect jobs in London Location \u2013 London Salary - \u00a329 - \u00a356K DOE Is this the best job spec you\u2019ve ever seen? Nearly every advert says the\u2026",
        "creation_date": "PostedPosted 30+ days ago",
        "saved_date": "2023-06-17"
    },
    {
        "name": "Landscape Architect",
        "company": "The Vero Studio",
        "location": "Hybrid remote in London SE1",
        "url": "https://uk.indeed.com/company/The-Vero-Studio/jobs/Landscape-Architect-f5012496d332dbe8?fccid=2b8fb9c8dc497026&vjs=3",
        "summary": "\nOrganize and be part of all the steps and tasks necessary to implement the landscape concept into a viable landscape scheme.\n",
        "creation_date": "EmployerActive 7 days ago",
        "saved_date": "2023-06-17"
    },
    {
        "name": "Senior or Principal Landscape Architect",
        "company": "FPCR",
        "location": "Derby DE74",
        "url": "https://uk.indeed.com/rc/clk?jk=fbbdb538fd34ce69&fccid=cca9edb7bdabf197&vjs=3",
        "summary": "\nExperience of concept design and detailed landscape design.\nWe are seeking talented individuals to help support the continued growth of the practice, working on\u2026\n",
        "creation_date": "PostedPosted 6 days ago",
        "saved_date": "2023-06-17"
    },
    {
        "name": "Senior Landscape Architect",
        "company": "Gillespies",
        "location": "Hybrid remote in London EC1R",
        "url": "https://uk.indeed.com/rc/clk?jk=91def264d6866154&fccid=2432fb25a19a4a82&vjs=3",
        "summary": "\nExperienced chartered landscape architects are welcome to apply.\nSuccessful candidates will ideally be CMLI, although not essential (an equivalent overseas\u2026\n",
        "creation_date": "PostedPosted 30+ days ago",
        "saved_date": "2023-06-17"
    },
    {
        "name": "Director or Associate Landscape Architect (LVIA specialist)",
        "company": "Pegasus Group",
        "location": "Hybrid remote in Edinburgh EH3",
        "url": "https://uk.indeed.com/company/Pegasus-Group/jobs/Landscape-Architect-9e354cf0ba270be3?fccid=cc2744d84b921175&vjs=3",
        "summary": "\nProven understanding and experience in LVIA\u2019s, feasibility studies, landscape planning and design, supporting landscape statements and mitigation strategies;\n",
        "creation_date": "EmployerActive 3 days ago",
        "saved_date": "2023-06-17"
    },
    {
        "name": "Principal Landscape Architect",
        "company": "Gillespies",
        "location": "Hybrid remote in London EC1R",
        "url": "https://uk.indeed.com/rc/clk?jk=2d8c7d526bda2c45&fccid=2432fb25a19a4a82&vjs=3",
        "summary": "\nSuccessful candidates will ideally be CMLI, although not essential (an equivalent overseas qualification would suffice), and have a strong interest and proven\u2026\n",
        "creation_date": "PostedPosted 30+ days ago",
        "saved_date": "2023-06-17"
    },
    {
        "name": "Landscape Architect jobs in Birmingham",
        "company": "Lead Careers",
        "location": "West Midlands+10 locations",
        "url": "https://uk.indeed.com/rc/clk?jk=e054b73a4ec3cae3&fccid=ce9f793e950d986a&vjs=3",
        "summary": "\nProject Landscape Architect \u2013 Warwickshire or Birmingham \u00a336-40k.\n",
        "creation_date": "PostedPosted 8 days ago",
        "saved_date": "2023-06-17"
    },
    {
        "name": "Garden Designer // Landscape Architect",
        "company": "North Hill Gardens Ltd",
        "location": "Glasgow G52",
        "url": "https://uk.indeed.com/company/North-Hill-Gardens-Ltd/jobs/Landscape-Architect-51aaa91c8d616870?fccid=b17b891556056393&vjs=3",
        "summary": "\nContribute to presenting landscape projects both verbally and graphically to potential clients.\nManage all phases of landscape project development with a focus\u2026\n",
        "creation_date": "EmployerActive 3 days ago",
        "saved_date": "2023-06-17"
    },
    {
        "name": "Landscape Architects",
        "company": "Stellar Recruitment Group",
        "location": "Hybrid remote in Newcastle upon Tyne",
        "url": "https://uk.indeed.com/company/Stellar-Recruitment-Group/jobs/Landscape-Architect-ef51e647bc89fb03?fccid=7e2cd544f87fc9fc&vjs=3",
        "summary": "\nJob Types: Full-time, Permanent.\n",
        "creation_date": "PostedPosted 30+ days ago",
        "saved_date": "2023-06-17"
    },
    {
        "name": "Assistant Garden/Landscape Designer",
        "company": "Consilium Hortus Ltd",
        "location": "Earls Colne",
        "url": "https://uk.indeed.com/company/Consilium-Hortus-Ltd/jobs/Landscape-Designer-5104607f394f3d26?fccid=93244e8ffcc3a2d3&vjs=3",
        "summary": "\nWe are looking for an assistant garden/landscape designer to assist the managing director/designer on a range of landscape and garden projects we are currently\u2026\n",
        "creation_date": "PostedPosted 30+ days ago",
        "saved_date": "2023-06-17"
    },
    {
        "name": "Landscape Architect",
        "company": "Amey",
        "location": "Manchester+1 location",
        "url": "https://uk.indeed.com/rc/clk?jk=8cde6eba844666fe&fccid=4f82f38de239d7c5&vjs=3",
        "summary": "\nInterest in all areas of landscape design and assessment.\nCollaborating with multidisciplinary teams to integrate landscape design into overall project plans.\n",
        "creation_date": "PostedPosted 30+ days ago",
        "saved_date": "2023-06-17"
    },
    {
        "name": "CMLI Qualified and Graduate Landscape Architects",
        "company": "Gillespies",
        "location": "Hybrid remote in Leeds",
        "url": "https://uk.indeed.com/rc/clk?jk=6f1f197e63825bbd&fccid=2432fb25a19a4a82&vjs=3",
        "summary": "\nSupport landscape planning and assessment fieldwork and surveys & assist with the preparation of landscape planning documents such as Landscape and Visual\u2026\n",
        "creation_date": "PostedPosted 30+ days ago",
        "saved_date": "2023-06-17"
    },
    {
        "name": "Landscape Designer",
        "company": "Storonsky",
        "location": "Remote",
        "url": "https://uk.indeed.com/rc/clk?jk=c2aa0efc7b2c9600&fccid=6098a5bc1618477b&vjs=3",
        "summary": "\nDegree qualification(s) in landscape architecture, architecture or urban design.\nThe successful applicant will manage the teams of design consultants to deliver\u2026\n",
        "creation_date": "EmployerActive 4 days ago",
        "saved_date": "2023-06-17"
    },
    {
        "name": "Senior or Principal Landscape Architect",
        "company": "Pegasus Group",
        "location": "Hybrid remote in Leeds",
        "url": "https://uk.indeed.com/company/Pegasus-Group/jobs/Senior-Landscape-Architect-10fe0e2ca0d65ef6?fccid=cc2744d84b921175&vjs=3",
        "summary": "\nWe provide landscape planning and landscape design services at various stages of the development process.\nIdeally, possess skills in AutoCAD/Vectorworks, Adobe\u2026\n",
        "creation_date": "EmployerActive 3 days ago",
        "saved_date": "2023-06-17"
    },
    {
        "name": "Landscape Architect",
        "company": "Horticruitment",
        "location": "West London",
        "url": "https://uk.indeed.com/company/Horticruitment/jobs/Landscape-Architect-aa4fe5acbd2ded89?fccid=b792afdc98f3bb26&vjs=3",
        "summary": "\nProfessional experience working in a landscape design studio.\nThey are looking to expand the team and bring in like-minded people who have a passion for all\u2026\n",
        "creation_date": "PostedPosted 30+ days ago",
        "saved_date": "2023-06-17"
    },
    {
        "name": "Consultant Landscape Architect",
        "company": "LUC",
        "location": "Hybrid remote in Glasgow",
        "url": "https://uk.indeed.com/company/LUC/jobs/Landscape-Architect-debe61e625f703c0?fccid=1b21bb24d59c05c8&vjs=3",
        "summary": "\nThe role will involve supporting senior team members on a diverse portfolio of projects.\nThere will also be the opportunity to support business development and\u2026\n",
        "creation_date": "EmployerActive 3 days ago",
        "saved_date": "2023-06-17"
    },
    {
        "name": "Senior Associate International Landscape Architect",
        "company": "Green Path Recruitment",
        "location": "Hybrid remote in London",
        "url": "https://uk.indeed.com/company/Green-Path-Recruitment/jobs/Senior-Landscape-Architect-6f55847a9f21e03f?fccid=c85409ba7f33052d&vjs=3",
        "summary": "\nIdeally you will have over 5 years landscape design consultancy experience mainly within the international market.\nLandscape Architecture: 4 years (preferred).\n",
        "creation_date": "PostedPosted 25 days ago",
        "saved_date": "2023-06-17"
    },
    {
        "name": "Garden Designer",
        "company": "Astek Landscapes Ltd",
        "location": "York YO41",
        "url": "https://uk.indeed.com/company/Astek-Landscapes-Ltd/jobs/Gardener-0172137cf398fa0b?fccid=307fac0536875ec6&vjs=3",
        "summary": "\nGarden designer Role to include the use of hand drawn design work and CAD software (type preferred to be agreed) for creating design proposals for predominantly\u2026\n",
        "creation_date": "EmployerActive 4 days ago",
        "saved_date": "2023-06-17"
    },
    {
        "name": "Grounds Maintenance Operatives",
        "company": "NURTURE LANDSCAPES GROUP",
        "location": "Yeovilton+9 locations",
        "url": "https://uk.indeed.com/company/Nurture-Landscapes-Group/jobs/Grounds-Maintenance-Worker-71cda9cdea4a69d0?fccid=225eec6330945e2d&vjs=3",
        "summary": "\nGavin Jones* provide landscape construction services to a wide variety of clients across the UK, working alongside landscape architects, designers and main\u2026\n",
        "creation_date": "EmployerActive 3 days ago",
        "saved_date": "2023-06-17"
    },
    {
        "name": "Soft Landscape Foreman",
        "company": "Landform Consultants",
        "location": "West London",
        "url": "https://uk.indeed.com/company/Landform-Consultants/jobs/Landscape-Foreman-7e67608c89395a45?fccid=0b098b6928c8b02c&vjs=3",
        "summary": "\nThey will also need to be a collaborative team worker, able to lead a soft landscaping team, whilst liaising effectively with other stakeholders such as\u2026\n",
        "creation_date": "EmployerActive 2 days ago",
        "saved_date": "2023-06-17"
    },
    {
        "name": "Landscape Architect with LVIA Skills",
        "company": "Lead Careers",
        "location": "Oxfordshire+1 location",
        "url": "https://uk.indeed.com/rc/clk?jk=ebb77be8e3282325&fccid=ce9f793e950d986a&vjs=3",
        "summary": "\nExperience in landscape character assessment and appraisal.\nAs a Landscape Architect you will have a special blend of skills combining landscape architecture\u2026\n",
        "creation_date": "PostedPosted 16 days ago",
        "saved_date": "2023-06-17"
    },
    {
        "name": "Graduate / Assistant Landscape Architect",
        "company": "Lead Careers",
        "location": "London",
        "url": "https://uk.indeed.com/rc/clk?jk=3d46773cb1ea2c8a&fccid=ce9f793e950d986a&vjs=3",
        "summary": "\nOur client is reputable Multi-Disciplinary Consultancy who are in need of an Graduate / Assistant Landscape Architect for their London studio.\n",
        "creation_date": "PostedPosted 25 days ago",
        "saved_date": "2023-06-17"
    },
    {
        "name": "Senior Landscape Architect with LVIA Skills",
        "company": "Lead Careers",
        "location": "London+2 locations",
        "url": "https://uk.indeed.com/rc/clk?jk=3b321e06be797df2&fccid=ce9f793e950d986a&vjs=3",
        "summary": "\nExperience in landscape character assessment and appraisal.\nAs a Senior Landscape Architect you will have a special blend of skills combining landscape\u2026\n",
        "creation_date": "PostedPosted 16 days ago",
        "saved_date": "2023-06-17"
    },
    {
        "name": "Consultant Landscape Planner/Architect",
        "company": "LUC",
        "location": "Hybrid remote in Manchester",
        "url": "https://uk.indeed.com/company/LUC/jobs/Landscape-Architect-d0e7ace6e6bd1c71?fccid=1b21bb24d59c05c8&vjs=3",
        "summary": "\nAssist in the preparation of landscape character and landscape sensitivity studies.\nAn interest or experience in Landscape and Visual Impact Assessments (LVIAs)\u2026\n",
        "creation_date": "EmployerActive 3 days ago",
        "saved_date": "2023-06-17"
    },
    {
        "name": "Senior or Principal Landscape Architects with experience in LVIAs",
        "company": "Endpoint Recruitment",
        "location": "Leeds",
        "url": "https://uk.indeed.com/company/Endpoint-Recruitment/jobs/Senior-Landscape-Architect-ff4ff56e9ebec61e?fccid=9bbaf0acbcea0271&vjs=3",
        "summary": "\nThey provide landscape planning and landscape design services at various stages of the development process.\nYou will primarily be involved in delivering LVIA\u2019s\u2026\n",
        "creation_date": "EmployerActive 17 days ago",
        "saved_date": "2023-06-17"
    },
    {
        "name": "Senior Landscape Architect",
        "company": "Amey",
        "location": "Manchester+1 location",
        "url": "https://uk.indeed.com/rc/clk?jk=39d60e52f20d6042&fccid=4f82f38de239d7c5&vjs=3",
        "summary": "\nAdvise on landscape aspects of projects including but not limited to EIAs, LVIAs, VIAs.\nKeep up to date with industry best practice and where, appropriate,\u2026\n",
        "creation_date": "PostedPosted 30+ days ago",
        "saved_date": "2023-06-17"
    },
    {
        "name": "Landscape Architect Planner",
        "company": "Hunter Mason",
        "location": "Hybrid remote in Leeds+1 location",
        "url": "https://uk.indeed.com/company/Hunter-Mason/jobs/Landscape-Architect-c545d03977178ca2?fccid=942131a66b68f6c5&vjs=3",
        "summary": "\nSenior Landscape Planner with experience in landscape/ townscape and a visual assessment to join their Manchester or Leeds studio to provide landscape planning\u2026\n",
        "creation_date": "PostedPosted 30+ days ago",
        "saved_date": "2023-06-17"
    },
    {
        "name": "Landscape Team Leader",
        "company": "Waratah Gardens Limited",
        "location": "Petworth",
        "url": "https://uk.indeed.com/company/Waratah-Gardens-Limited/jobs/Landscape-Technician-5b7f876f70a2af2b?fccid=692afd4722655e81&vjs=3",
        "summary": "\nAble to read and understand contract/architect drawings and implement them on site.\nSupervise and manage a small team of landscapers, while ensuring compliance\u2026\n",
        "creation_date": "EmployerActive 9 days ago",
        "saved_date": "2023-06-17"
    },
    {
        "name": "Graduate Landscape Architect",
        "company": "Lead Careers",
        "location": "Tyne and Wear+6 locations",
        "url": "https://uk.indeed.com/rc/clk?jk=4a822492d1ff5dc0&fccid=ce9f793e950d986a&vjs=3",
        "summary": "\nWe are looking for a motivated, well organised and talented Graduate Landscape Architect for a studio in Tyne & Wear.\nA full UK driving licence.\n",
        "creation_date": "PostedPosted 30+ days ago",
        "saved_date": "2023-06-17"
    },
    {
        "name": "Principal Landscape Architect",
        "company": "E3P",
        "location": "Hybrid remote in Manchester",
        "url": "https://uk.indeed.com/company/e3p/jobs/Landscape-Architect-a0185ebf29d91ee2?fccid=d4cb271b2783f527&vjs=3",
        "summary": "\nProvide technical guidance and expertise to both the landscape and ecology team, and also the wider disciplines at E3P, review project designs and reports and\u2026\n",
        "creation_date": "EmployerActive 4 days ago",
        "saved_date": "2023-06-17"
    },
    {
        "name": "Assistant Landscape Architect",
        "company": "Lead Careers",
        "location": "Wiltshire+7 locations",
        "url": "https://uk.indeed.com/rc/clk?jk=cadb26903348d925&fccid=ce9f793e950d986a&vjs=3",
        "summary": "\nDue to an increase in work, they are urgently seeking an Assistant level Landscape Architect for their Wiltshire studio.\n",
        "creation_date": "PostedPosted 16 days ago",
        "saved_date": "2023-06-17"
    },
    {
        "name": "Senior Landscape Architect",
        "company": "Ready Careers",
        "location": "Manchester+2 locations",
        "url": "https://uk.indeed.com/rc/clk?jk=381d205c61309a25&fccid=6c103207f0ac9d8a&vjs=3",
        "summary": "\nAt least 5 years working on UK projects, a varied portfolio of sizeable projects would be ideal.\nExciting creative flair coupled with technical expertise.\n",
        "creation_date": "PostedPosted 30+ days ago",
        "saved_date": "2023-06-17"
    },
    {
        "name": "Associate Landscape Architect",
        "company": "Lead Careers",
        "location": "Oxfordshire+2 locations",
        "url": "https://uk.indeed.com/company/Lead-Careers/jobs/Landscape-Architect-db44d2921c8151ef?fccid=ce9f793e950d986a&vjs=3",
        "summary": "\nA degree/post graduate degree in Landscape Architecture.\nA Chartered Member of the Landscape Institute (CMLI).\nHave good written and communication abilities.\n",
        "creation_date": "PostedPosted 30+ days ago",
        "saved_date": "2023-06-17"
    },
    {
        "name": "Garden Designer",
        "company": "We Love Plants Ltd",
        "location": "Redhill",
        "url": "https://uk.indeed.com/company/We-Love-Plants-LTD/jobs/Gardener-8bf170279329fcb5?fccid=76725e0f5bac184a&vjs=3",
        "summary": "\nYou will be ambitious, hard working and enthusiastic, with a passion for design and planting.\nProducing project mood boards and imagery for presentations.\n",
        "creation_date": "EmployerActive 4 days ago",
        "saved_date": "2023-06-17"
    },
    {
        "name": "Principal to Associate Director Landscape Architect",
        "company": "Lead Careers",
        "location": "Hybrid remote in Scotland",
        "url": "https://uk.indeed.com/rc/clk?jk=5274d5b18af91ec9&fccid=ce9f793e950d986a&vjs=3",
        "summary": "\nProject work will range from high profile strategic residential and urban regeneration schemes through to detailed public realm design.\n",
        "creation_date": "PostedPosted 30+ days ago",
        "saved_date": "2023-06-17"
    },
    {
        "name": "Grounds Assistant",
        "company": "Luton Hoo Hotel, Golf & Spa",
        "location": "Luton LU1",
        "url": "https://uk.indeed.com/rc/clk?jk=3b7622efa4ec77a8&fccid=625dfe005756d101&vjs=3",
        "summary": "\nUnderstand and be aware of the history of the Estate, including architects and landscape gardeners and how they have influenced and developed Luton Hoo.\n",
        "creation_date": "EmployerActive 22 days ago",
        "saved_date": "2023-06-17"
    },
    {
        "name": "Senior Landscape Architect",
        "company": "Alfred Recruitment",
        "location": "Truro",
        "url": "https://uk.indeed.com/company/Alfred-Recruitment/jobs/Senior-Landscape-Architect-d88683e398934d34?fccid=33e8f288d0cc054c&vjs=3",
        "summary": "\nExperience of landscape and urban design relating to new development and regeneration;\nYou will produce landscape and visual impact assessments for 'standalone'\u2026\n",
        "creation_date": "PostedPosted 30+ days ago",
        "saved_date": "2023-06-17"
    },
    {
        "name": "Principal Landscape Architect",
        "company": "Lead Careers",
        "location": "Hybrid remote in Greater Manchester+1 location",
        "url": "https://uk.indeed.com/rc/clk?jk=205ac98b601646a0&fccid=ce9f793e950d986a&vjs=3",
        "summary": "\nYou will provide specialist consultancy advice for landscape design, landscape management and landscape planning.\nA full UK driving licence.\n",
        "creation_date": "PostedPosted 25 days ago",
        "saved_date": "2023-06-17"
    },
    {
        "name": "Senior Landscape Architect",
        "company": "Horticruitment",
        "location": "Hybrid remote in Brighton",
        "url": "https://uk.indeed.com/company/Horticruitment/jobs/Senior-Landscape-Architect-6ab8afed57cd8ff6?fccid=b792afdc98f3bb26&vjs=3",
        "summary": "\nProfessional experience working in a landscape design studio.\nThe Senior Landscape Architect will direct the delivery of the development, design, and co\u2026\n",
        "creation_date": "PostedPosted 30 days ago",
        "saved_date": "2023-06-17"
    },
    {
        "name": "Assistant & Senior Landscape Architects",
        "company": "Lead Careers",
        "location": "Buckinghamshire",
        "url": "https://uk.indeed.com/rc/clk?jk=9a5fee9f1cf5ad7c&fccid=ce9f793e950d986a&vjs=3",
        "summary": "\nWhile the Pandemic has interrupted certain workflows, the Practice seems to have been very lucky and experiencing a solid increase in work.\n",
        "creation_date": "PostedPosted 16 days ago",
        "saved_date": "2023-06-17"
    },
    {
        "name": "Gardener",
        "company": "NURTURE LANDSCAPES GROUP",
        "location": "Slough SL1",
        "url": "https://uk.indeed.com/company/Nurture-Landscapes-Group/jobs/Gardener-1a26235542503780?fccid=225eec6330945e2d&vjs=3",
        "summary": "\nGavin Jones* provide landscape construction services to a wide variety of clients across the UK, working alongside landscape architects, designers and main\u2026\n",
        "creation_date": "EmployerActive 9 days ago",
        "saved_date": "2023-06-17"
    },
    {
        "name": "Principal/Associate Landscape Architect",
        "company": "Lead Careers",
        "location": "Devon",
        "url": "https://uk.indeed.com/rc/clk?jk=53bcd6cec3088ed8&fccid=ce9f793e950d986a&vjs=3",
        "summary": "\nLEAD is working with a Landscape Architecture Studio in Devon who are looking to bring in a Principal/Associate Landscape Architect to their design team and be\u2026\n",
        "creation_date": "PostedPosted 30+ days ago",
        "saved_date": "2023-06-17"
    },
    {
        "name": "Mobile Gardener",
        "company": "NURTURE LANDSCAPES GROUP",
        "location": "London",
        "url": "https://uk.indeed.com/company/Nurture-Landscapes-Group/jobs/Gardener-81de52c2c153219a?fccid=225eec6330945e2d&vjs=3",
        "summary": "\nGavin Jones* provide landscape construction services to a wide variety of clients across the UK, working alongside landscape architects, designers and main\u2026\n",
        "creation_date": "EmployerActive 3 days ago",
        "saved_date": "2023-06-17"
    },
    {
        "name": "Landscape Team Leader",
        "company": "Gavin Jones Ltd",
        "location": "Mirfield",
        "url": "https://uk.indeed.com/company/Nurture-Landscapes-Group/jobs/Landscape-Technician-7315250d654aa158?fccid=225eec6330945e2d&vjs=3",
        "summary": "\nThe ability to interpret architects\u2019 drawings and set out working areas for operational teams.\nOur Team Leader would be expected to oversee the soft landscaping\u2026\n",
        "creation_date": "EmployerActive 5 days ago",
        "saved_date": "2023-06-17"
    },
    {
        "name": "Landscape Architect",
        "company": "Ready Careers",
        "location": "Plymouth",
        "url": "https://uk.indeed.com/rc/clk?jk=2d3353922c836bbf&fccid=6c103207f0ac9d8a&vjs=3",
        "summary": "\nYour responsibilities will include producing graphical plans and presentation documents for early-stage client and stakeholder engagement.\n",
        "creation_date": "PostedPosted 30+ days ago",
        "saved_date": "2023-06-17"
    },
    {
        "name": "Landscape Architect with LVIA",
        "company": "Lead Careers",
        "location": "Hampshire",
        "url": "https://uk.indeed.com/rc/clk?jk=d72a95c71d2a8c69&fccid=ce9f793e950d986a&vjs=3",
        "summary": "\nExperience in delivering planning applications, dealing with client and landscape contractors.\nA minimum of 2 years of professional experience in delivering UK\u2026\n",
        "creation_date": "PostedPosted 30+ days ago",
        "saved_date": "2023-06-17"
    },
    {
        "name": "Sole Gardener",
        "company": "English Country Gardeners",
        "location": "Kent",
        "url": "https://uk.indeed.com/company/English-Country-Gardeners/jobs/Gardener-8f5344522afbf4b5?fccid=7a95fe040a716953&vjs=3",
        "summary": "\nThe client has recently put the wheels in motion to enhance the gardens, with the assistance of a landscape architect and are in the process of installing new\u2026\n",
        "creation_date": "EmployerActive 22 days ago",
        "saved_date": "2023-06-17"
    },
    {
        "name": "Gardener",
        "company": "Richstone Properties - Templeton House",
        "location": "Roehampton",
        "url": "https://uk.indeed.com/company/Richstone-Properties/jobs/Gardener-8d0faa891419356a?fccid=b0e88f06a849a333&vjs=3",
        "summary": "\nThe Head Gardener is seeking to employ a Gardener with 3 to 5 years\u2019 experience who will have excellent horticultural knowledge and a passion for maintaining\u2026\n",
        "creation_date": "EmployerActive 8 days ago",
        "saved_date": "2023-06-17"
    },
    {
        "name": "Senior/Principal Landscape Architect",
        "company": "Lead Careers",
        "location": "South Yorkshire",
        "url": "https://uk.indeed.com/rc/clk?jk=b0142cfbc6b728c7&fccid=ce9f793e950d986a&vjs=3",
        "summary": "\nStrong conceptual landscape and public realm design skills.\nThey are looking for a Senior or Principal Landscape architect with a creative and open outlook and\u2026\n",
        "creation_date": "PostedPosted 8 days ago",
        "saved_date": "2023-06-17"
    },
    {
        "name": "Senior Landscape Architect",
        "company": "Flagship Consulting",
        "location": "Hybrid remote in Cambridge",
        "url": "https://uk.indeed.com/company/Flagship-Consulting/jobs/Senior-Landscape-Architect-db459871862d5ebd?fccid=4b38237f6f821084&vjs=3",
        "summary": "\nThorough knowledge and understanding of the UK legal and planning system with respect to landscape architecture.\nVitality Health Care - Private Medical Scheme.\n",
        "creation_date": "PostedPosted 15 days ago",
        "saved_date": "2023-06-17"
    },
    {
        "name": "Chartered/Senior/Associate Landscape Architect",
        "company": "BDP",
        "location": "Hybrid remote in Bristol BS1",
        "url": "https://uk.indeed.com/company/BDP/jobs/Senior-Landscape-Architect-2f77e36f572a682e?fccid=b6a306d97e8c39a4&vjs=3",
        "summary": "\nCandidates will need to have strong design and technical skills, and contribute to a large, evolving, and exciting programme of work.\n",
        "creation_date": "PostedPosted 30+ days ago",
        "saved_date": "2023-06-17"
    },
    {
        "name": "Arborist",
        "company": "Southern Ecological Solutions Ltd (SES)",
        "location": "Billericay",
        "url": "https://uk.indeed.com/rc/clk?jk=39f0f428f947e116&fccid=875332299c84faa0&vjs=3",
        "summary": "\nIn return, we offer excellent benefits including a bonus scheme, high-quality training opportunities and the chance to progress your career.\n",
        "creation_date": "EmployerActive 4 days ago",
        "saved_date": "2023-06-17"
    },
    {
        "name": "Associate Director Landscape Architect",
        "company": "Lead Careers",
        "location": "London",
        "url": "https://uk.indeed.com/rc/clk?jk=22d16d6b85deecf7&fccid=ce9f793e950d986a&vjs=3",
        "summary": "\nA wide range of expertise in all areas of landscape planning and design.\nProjects include Masterplanning new towns and mixed-use developments to town centre\u2026\n",
        "creation_date": "PostedPosted 30+ days ago",
        "saved_date": "2023-06-17"
    },
    {
        "name": "Arborist",
        "company": "NURTURE LANDSCAPES HOLDINGS LIMITED",
        "location": "Tidworth ED+1 location",
        "url": "https://uk.indeed.com/company/Nurture-Landscapes-Group/jobs/Arborist-b6285f82dfc24002?fccid=225eec6330945e2d&vjs=3",
        "summary": "\nGavin Jones* provide landscape construction services to a wide variety of clients across the UK, working alongside landscape architects, designers and main\u2026\n",
        "creation_date": "EmployerActive 8 days ago",
        "saved_date": "2023-06-17"
    },
    {
        "name": "SKILLED HARD LANDSCAPER",
        "company": "Landscape Associates Ltd",
        "location": "London",
        "url": "https://uk.indeed.com/company/Landscape-Associates-Ltd/jobs/Landscape-Technician-f263f5f924a8e062?fccid=7c2bc5358c51e15c&vjs=3",
        "summary": "\nRight to live and work in the UK.\nGood level of spoken English.\nPrevious experience in Landscape Construction.\nGood plant and horticultural knowledge.\n",
        "creation_date": "EmployerActive 2 days ago",
        "saved_date": "2023-06-17"
    },
    {
        "name": "Chartered Landscape Architect",
        "company": "Lead Careers",
        "location": "Hertfordshire+3 locations",
        "url": "https://uk.indeed.com/rc/clk?jk=ef3934b06c62e86a&fccid=ce9f793e950d986a&vjs=3",
        "summary": "\nDemonstrable experience in the production of hard landscape design and detailing.\nThe ability to take responsibility for the daily running of landscape projects\u2026\n",
        "creation_date": "PostedPosted 30+ days ago",
        "saved_date": "2023-06-17"
    },
    {
        "name": "Grounds Maintenance Operative",
        "company": "NURTURE LANDSCAPES HOLDINGS LIMITED",
        "location": "Blandford Forum",
        "url": "https://uk.indeed.com/company/Nurture-Landscapes-Group/jobs/Grounds-Maintenance-Worker-23cedfa4f94261ff?fccid=225eec6330945e2d&vjs=3",
        "summary": "\nGavin Jones* provide landscape construction services to a wide variety of clients across the UK, working alongside landscape architects, designers and main\u2026\n",
        "creation_date": "EmployerActive 5 days ago",
        "saved_date": "2023-06-17"
    },
    {
        "name": "Garden Maintenance Operative",
        "company": "Randle Siddeley",
        "location": "London",
        "url": "https://uk.indeed.com/rc/clk?jk=4d99de34a5007193&fccid=949daf12131d80d4&vjs=3",
        "summary": "\nWe specialises in designing landscapes and gardens for private and commercial clients worldwide and pride ourselves on our experienced landscape architects and\u2026\n",
        "creation_date": "PostedPosted 30+ days ago",
        "saved_date": "2023-06-17"
    },
    {
        "name": "Senior Landscape Architect (Design Based)",
        "company": "Lead Careers",
        "location": "Worcestershire",
        "url": "https://uk.indeed.com/rc/clk?jk=03cc9feb9df357d7&fccid=ce9f793e950d986a&vjs=3",
        "summary": "\nThe role will involve providing landscape planning and landscape design input to projects whilst also growing strong client and project team relationships,\u2026\n",
        "creation_date": "PostedPosted 30+ days ago",
        "saved_date": "2023-06-17"
    },
    {
        "name": "Grounds Maintenance Supervisor",
        "company": "NURTURE LANDSCAPES GROUP",
        "location": "Reading RG2",
        "url": "https://uk.indeed.com/company/Nurture-Landscapes-Group/jobs/Grounds-Maintenance-Worker-dbf176d488f3a4e0?fccid=225eec6330945e2d&vjs=3",
        "summary": "\nGavin Jones* provide landscape construction services to a wide variety of clients across the UK, working alongside landscape architects, designers and main\u2026\n",
        "creation_date": "PostedToday",
        "saved_date": "2023-06-17"
    },
    {
        "name": "Senior / Associate Landscape Architect",
        "company": "Lead Careers",
        "location": "London",
        "url": "https://uk.indeed.com/rc/clk?jk=fdae61e8b57df774&fccid=ce9f793e950d986a&vjs=3",
        "summary": "\nThe ideal candidate will have experience managing a team across a wide range of projects, providing mentoring, guidance and project leader skills to run and\u2026\n",
        "creation_date": "PostedPosted 30+ days ago",
        "saved_date": "2023-06-17"
    },
    {
        "name": "Gardener",
        "company": "OCR Solutions",
        "location": "Reading",
        "url": "https://uk.indeed.com/company/OCR-Solutions/jobs/Gardener-976b94a56e571388?fccid=92ed431ffd8dd11f&vjs=3",
        "summary": "\nFollow instructions from supervisor or landscape architect.\nThe successful candidate will be responsible for maintaining the grounds of our property, including\u2026\n",
        "creation_date": "PostedPosted 2 days ago",
        "saved_date": "2023-06-17"
    },
    {
        "name": "Landscape Architects - Chartered, Senior and Associate",
        "company": "Ready Careers",
        "location": "Hybrid remote in Bristol",
        "url": "https://uk.indeed.com/rc/clk?jk=79aa19c7743aa162&fccid=6c103207f0ac9d8a&vjs=3",
        "summary": "\nHave a minimum of 2 years experience after Chartership.\nShow experience on medium - large scale projects from concept through to delivery.\n",
        "creation_date": "PostedPosted 30+ days ago",
        "saved_date": "2023-06-17"
    },
    {
        "name": "Seasonal Grounds Maintenance Operative",
        "company": "NURTURE LANDSCAPES HOLDINGS LIMITED",
        "location": "Bristol+1 location",
        "url": "https://uk.indeed.com/company/Nurture-Landscapes-Group/jobs/Grounds-Maintenance-Worker-3b1ef48fbc120f0e?fccid=225eec6330945e2d&vjs=3",
        "summary": "\nGavin Jones* provide landscape construction services to a wide variety of clients across the UK, working alongside landscape architects, designers and main\u2026\n",
        "creation_date": "EmployerActive 4 days ago",
        "saved_date": "2023-06-17"
    },
    {
        "name": "Interior Plant Supervisor (Horticulture)",
        "company": "NURTURE LANDSCAPES GROUP",
        "location": "Upminster",
        "url": "https://uk.indeed.com/company/Nurture-Landscapes-Group/jobs/Plant-Supervisor-c10ff3c13d808558?fccid=225eec6330945e2d&vjs=3",
        "summary": "\nGavin Jones* provide landscape construction services to a wide variety of clients across the UK, working alongside landscape architects, designers and main\u2026\n",
        "creation_date": "EmployerActive 3 days ago",
        "saved_date": "2023-06-17"
    },
    {
        "name": "Landscape Operative",
        "company": "NURTURE LANDSCAPES HOLDINGS LIMITED",
        "location": "Mirfield",
        "url": "https://uk.indeed.com/company/Nurture-Landscapes-Group/jobs/Landscape-Technician-6c9146bae9218724?fccid=225eec6330945e2d&vjs=3",
        "summary": "\nOur Landscapers would be expected to carry out soft landscaping activities on high end commercial projects such as art galleries, hotel\u2019s, business & retail\u2026\n",
        "creation_date": "EmployerActive 4 days ago",
        "saved_date": "2023-06-17"
    },
    {
        "name": "Landscape Contract Manager",
        "company": "HL Services",
        "location": "West Berkshire",
        "url": "https://uk.indeed.com/rc/clk?jk=1e54dd5ace3f9d56&fccid=caad442e6b3443f9&vjs=3",
        "summary": "\nConsulting with clients, site manager, quantity surveyors, landscape architects etc.\nAssist landscape Operations Manager with setting out.\n",
        "creation_date": "PostedPosted 17 days ago",
        "saved_date": "2023-06-17"
    },
    {
        "name": "Mobile Grounds Maintenance Operative",
        "company": "NURTURE LANDSCAPES GROUP",
        "location": "Upminster+2 locations",
        "url": "https://uk.indeed.com/company/Nurture-Landscapes-Group/jobs/Grounds-Maintenance-Worker-8e152cee77ed3d35?fccid=225eec6330945e2d&vjs=3",
        "summary": "\nGavin Jones* provide landscape construction services to a wide variety of clients across the UK, working alongside landscape architects, designers and main\u2026\n",
        "creation_date": "EmployerActive 3 days ago",
        "saved_date": "2023-06-17"
    },
    {
        "name": "Grounds Maintenance Team Leader",
        "company": "NURTURE LANDSCAPES GROUP",
        "location": "Redhill",
        "url": "https://uk.indeed.com/company/Nurture-Landscapes-Group/jobs/Grounds-Maintenance-Worker-4ac6f6877bb3327b?fccid=225eec6330945e2d&vjs=3",
        "summary": "\nGavin Jones* provide landscape construction services to a wide variety of clients across the UK, working alongside landscape architects, designers and main\u2026\n",
        "creation_date": "EmployerActive 8 days ago",
        "saved_date": "2023-06-17"
    },
    {
        "name": "Arborist Team Leader",
        "company": "NURTURE LANDSCAPES HOLDINGS LIMITED",
        "location": "Plymouth",
        "url": "https://uk.indeed.com/company/Nurture-Landscapes-Group/jobs/Arborist-ac9ccc26057cf516?fccid=225eec6330945e2d&vjs=3",
        "summary": "\nGavin Jones* provide landscape construction services to a wide variety of clients across the UK, working alongside landscape architects, designers and main\u2026\n",
        "creation_date": "EmployerActive 8 days ago",
        "saved_date": "2023-06-17"
    }
]